{
"url": "http://www.alice.org/index.php?page=what_is_alice/what_is_alice",
"name": "Alice.org",
"dateAdd": "2017-12-31T07:13:31.000Z",
"dateUpdate": "2019-05-13T06:39:25.849Z",
"id": "63e3dd89-f641-4277-b8e6-5a80e13d7464",
"type": "url",
"tags": [ "academia", "carnagie-mellon", ] ,
"images": [],
"description": ""
},{
"url": "http://www.alice.org/",
"name": "Alice: Free, Easy, Interactive 3D Graphics for the WWW",
"dateAdd": "2017-12-31T07:13:31.000Z",
"dateUpdate": "2019-05-19T03:22:25.366Z",
"id": "268d7ed1-5b4d-45b9-87f6-c6ee4159b6e9",
"type": "url",
"tags": [ "academia", "carnagie-mellon", ] ,
"images": [],
"description": ""
},{
"url": "https://github.com/architecture-building-systems/RC_BuildingSimulator/wiki/10min-guide-to-your-first-simulation",
"name": "10min guide to your first simulation · architecture-building-systems/RC_BuildingSimulator Wiki",
"dateAdd": "2017-12-31T07:13:28.000Z",
"dateUpdate": "2019-05-19T03:27:31.772Z",
"id": "e3b71595-f0ad-43e3-a0fd-26848657d8b7",
"type": "url",
"tags": [ "academia", "eth-zurich", ] ,
"images": [],
"description": ""
},{
"url": "http://institutewithoutboundaries.ca/",
"name": "Institute without Boundaries – Interdisciplinary Design Strategy",
"dateAdd": "2018-07-21T19:39:42.154Z",
"dateUpdate": "2019-05-19T03:31:27.828Z",
"id": "16e6d63a-5ecb-4ce4-80b4-2b2a9d5388f7",
"type": "url",
"tags": [ "academia", "george-brown", ] ,
"images": [],
"description": ""
},{
"url": "http://nailo.media.mit.edu/",
"name": "NailO | MIT Media Lab",
"dateAdd": "2018-07-19T08:06:14.583Z",
"dateUpdate": "2019-05-19T03:34:30.384Z",
"id": "68aaf2b5-24eb-460c-b92f-9cef6704e27c",
"type": "url",
"tags": [ "academia", "mit", "mit" ] ,
"images": [],
"description": ""
},{
"url": "https://selfassemblylab.mit.edu/",
"name": "Self-Assembly Lab",
"dateAdd": "2018-07-19T08:07:05.082Z",
"dateUpdate": "2019-05-19T03:36:03.552Z",
"id": "044a96cb-12fc-4fb5-bcd1-e2c3193c9f76",
"type": "url",
"tags": [ "academia", "mit", "mit" ] ,
"images": [],
"description": ""
},{
"url": "http://senseable.mit.edu/osarc/",
"name": "Open Source Architecture",
"dateAdd": "2017-12-31T19:33:50.000Z",
"dateUpdate": "2019-05-19T04:00:08.337Z",
"id": "5647dd46-5dde-4605-8b57-ae11124c3059",
"type": "url",
"tags": [ "academia", "mit", "mit" ] ,
"images": [],
"description": ""
},{
"url": "https://issuu.com/antonshynkaruk/docs/ods_manual_v1",
"name": "Ods manual v1 by Anton Shynkaruk - issuu",
"dateAdd": "2018-07-21T20:19:10.137Z",
"dateUpdate": "2019-05-19T04:06:29.029Z",
"id": "abf30f9e-4580-493b-b19a-2759927113aa",
"type": "url",
"tags": [ "academia", "open-design-school", ] ,
"images": [],
"description": ""
},{
"url": "https://ods.matera-basilicata2019.it/en/about",
"name": "About",
"dateAdd": "2018-07-21T20:08:33.566Z",
"dateUpdate": "2019-05-19T04:04:24.888Z",
"id": "dec2f6ef-2dc7-4ee7-a118-ebb6ea600f50",
"type": "url",
"tags": [ "academia", "open-design-school", ] ,
"images": [],
"description": ""
},{
"url": "https://ods.matera-basilicata2019.it/en/",
"name": "Blog",
"dateAdd": "2018-07-24T03:41:07.104Z",
"dateUpdate": "2019-05-19T04:04:35.296Z",
"id": "c5d7b637-e470-4130-8e72-7a9126c38f03",
"type": "url",
"tags": [ "academia", "open-design-school", ] ,
"images": [],
"description": ""
},{
"url": "http://zeta.math.utsa.edu/~yxk833/InfoCities.html",
"name": ""The Information Architecture of  Cities", by L. Andrew Coward and Nikos A. Salingaros",
"dateAdd": "2018-07-19T08:08:23.462Z",
"dateUpdate": "2019-05-19T21:01:00.983Z",
"id": "0c508bda-654b-4dd5-8f29-808709a638a6",
"type": "url",
"tags": [ "articles / videos", "2005", ] ,
"images": [],
"description": ""
},{
"url": "https://www.dezeen.com/2009/11/11/openstructures-by-thomas-lommee/",
"name": "OpenStructures by Thomas Lommée | Dezeen",
"dateAdd": "2018-07-21T19:42:07.159Z",
"dateUpdate": "2019-03-03T01:09:12.779Z",
"id": "7b9b12f1-a364-439c-a9f5-94c34188a835",
"type": "url",
"tags": [ "articles / videos", "2009", "dezeen" ] ,
"images": [],
"description": ""
},{
"url": "http://www.intrastructures.net/yes_we_re_open.pdf",
"name": "yes_we_re_open.pdf",
"dateAdd": "2018-07-21T19:54:10.763Z",
"dateUpdate": "2019-04-14T08:44:12.448Z",
"id": "38795e47-602f-447e-875f-30c40668158a",
"type": "url",
"tags": [ "articles / videos", "2010", ] ,
"images": [],
"description": ""
},{
"url": "https://www.comparebusinessproducts.com/fyi/open-source-open-world",
"name": "Open Source Open World",
"dateAdd": "2018-07-21T19:58:32.563Z",
"dateUpdate": "2019-02-12T04:43:53.438Z",
"id": "bd9f3179-d67b-4236-9a38-e14c027469d4",
"type": "url",
"tags": [ "articles / videos", "2010", ] ,
"images": [],
"description": ""
},{
"url": "https://web.archive.org/web/20120709034513/http://ulab.cca.edu/2011/06/opspace/",
"name": "(OP)space – ulab",
"dateAdd": "2018-07-19T07:33:36.577Z",
"dateUpdate": "2019-04-14T08:12:09.780Z",
"id": "984c04f9-d349-4e94-849e-a3032550b288",
"type": "url",
"tags": [ "articles / videos", "2010", ] ,
"images": [],
"description": ""
},{
"url": "https://www.comparebusinessproducts.com/fyi/open-source-open-world",
"name": "Open Source Open World",
"dateAdd": "2018-07-20T08:32:20.999Z",
"dateUpdate": "2019-02-12T04:43:53.438Z",
"id": "12b20b8e-d18d-4ee7-a75a-20d359ece8a3",
"type": "url",
"tags": [ "articles / videos", "2010", ] ,
"images": [],
"description": ""
},{
"url": "http://www.calit2.net/newsroom/release.php?id=1873",
"name": "Calit2 : CAVE-CAD Software Will Help Mine Human Brain to Improve Architectural Design",
"dateAdd": "2017-12-31T19:33:49.000Z",
"dateUpdate": "2018-07-24T03:37:03.579Z",
"id": "16d138e9-743e-413c-9bab-e26a4570c70a",
"type": "url",
"tags": [ "articles / videos", "2011", ] ,
"images": [],
"description": ""
},{
"url": "http://aiad8.prod.acquia-sites.com/sites/default/files/2016-04/Energy-Modeling-Design-Process-Guide.pdf",
"name": "Energy-Modeling-Design-Process-Guide.pdf",
"dateAdd": "2018-07-22T01:14:05.184Z",
"dateUpdate": "2019-04-14T07:25:49.468Z",
"id": "a8663383-a5fa-4233-83c7-2d531d605850",
"type": "url",
"tags": [ "articles / videos", "2012", ] ,
"images": [],
"description": ""
},{
"url": "http://www.haque.co.uk/opensourcearchitecture.php",
"name": "haque :: design + research",
"dateAdd": "2018-07-24T03:51:08.817Z",
"dateUpdate": "2019-03-02T07:46:22.646Z",
"id": "fad76fe2-a1a9-4da5-9fd5-f3b0089a91ca",
"type": "url",
"tags": [ "articles / videos", "2012", ] ,
"images": [],
"description": ""
},{
"url": "https://www.ted.com/talks/skylar_tibbits_the_emergence_of_4d_printing",
"name": "Skylar Tibbits: The emergence of "4D printing" | TED Talk",
"dateAdd": "2018-07-24T04:05:33.303Z",
"dateUpdate": "2018-07-24T04:05:33.303Z",
"id": "ee46b8a2-7679-4fef-a712-a750bcbb240d",
"type": "url",
"tags": [ "articles / videos", "2013", ] ,
"images": [],
"description": ""
},{
"url": "https://www.shareable.net/blog/6-stunning-open-source-house-designs-from-paperhouses",
"name": "6 Stunning Open Source House Designs from Paperhouses - Shareable",
"dateAdd": "2018-07-19T07:25:43.283Z",
"dateUpdate": "2018-07-21T19:42:16.035Z",
"id": "c04b3b8f-2090-4fa6-a421-03a5c2dd0de7",
"type": "url",
"tags": [ "articles / videos", "2014", ] ,
"images": [],
"description": ""
},{
"url": "http://www.didiy.eu/blogs/trajectories-design-digital-diy",
"name": "Trajectories of Design for Digital DIY | Digital DIY",
"dateAdd": "2018-07-21T20:23:29.207Z",
"dateUpdate": "2018-07-21T20:23:29.207Z",
"id": "2706db53-ff13-450a-b63b-cd324040e523",
"type": "url",
"tags": [ "articles / videos", "2015", ] ,
"images": [],
"description": ""
},{
"url": "https://inhabitat.com/this-tiny-e-mailable-solar-house-snaps-together-like-a-3d-puzzle-without-a-single-nail/",
"name": "This tiny "e-mailable" solar house snaps together like a 3D puzzle without a single nail | Inhabitat - Green Design, Innovation, Architecture, Green Building",
"dateAdd": "2018-07-19T08:20:42.841Z",
"dateUpdate": "2018-07-24T03:58:21.431Z",
"id": "cb43735f-b0be-4476-ba88-5f92a28034ea",
"type": "url",
"tags": [ "articles / videos", "2015", "eth" ] ,
"images": [],
"description": ""
},{
"url": "https://news.ycombinator.com/item?id=11032428",
"name": "This House Costs Just $20,000–But It’s Nicer Than Yours | Hacker News",
"dateAdd": "2017-12-31T19:33:49.000Z",
"dateUpdate": "2018-07-24T03:54:41.750Z",
"id": "39a687e8-c079-4bc5-91f1-71e78d4ede44",
"type": "url",
"tags": [ "articles / videos", "2016", ] ,
"images": [],
"description": ""
},{
"url": "https://news.ycombinator.com/item?id=12893040",
"name": "Open-Source 3D Graphics Design: Where to Begin | Hacker News",
"dateAdd": "2017-12-31T19:33:48.000Z",
"dateUpdate": "2018-07-24T04:36:35.901Z",
"id": "ca801973-d2d4-4d63-acb6-ffac78b1096d",
"type": "url",
"tags": [ "articles / videos", "2016", ] ,
"images": [],
"description": ""
},{
"url": "https://www.telegraph.co.uk/technology/2016/04/23/the-water-purifier-that-also-generates-electricity-and-creates-w/",
"name": "This water purifier generates electricity and creates Wi-Fi connections",
"dateAdd": "2018-07-24T04:45:04.814Z",
"dateUpdate": "2018-07-24T04:45:04.815Z",
"id": "8851ae41-53dd-42ef-916a-a92b0eba2c24",
"type": "url",
"tags": [ "articles / videos", "2016", ] ,
"images": [],
"description": ""
},{
"url": "https://www.dezeen.com/2016/08/10/avava-britespace-tiny-house-flat-pack-micro-dwelling-easy-transportation-assembly/",
"name": "Avava's tiny house represents "completely new way to do prefab"",
"dateAdd": "2018-07-24T04:51:30.267Z",
"dateUpdate": "2018-07-24T04:51:30.268Z",
"id": "d03031ba-479a-4a7b-8ade-1679266935ba",
"type": "url",
"tags": [ "articles / videos", "2016", "dezeen" ] ,
"images": [],
"description": ""
},{
"url": "https://www.currentaffairs.org/2017/10/why-you-hate-contemporary-architecture",
"name": "Why You Hate Contemporary Architecture | Current Affairs",
"dateAdd": "2018-07-14T09:07:29.712Z",
"dateUpdate": "2018-07-24T03:53:03.611Z",
"id": "5abf3431-2ae6-47c0-8702-f27bff8daf40",
"type": "url",
"tags": [ "articles / videos", "2017", ] ,
"images": [],
"description": ""
},{
"url": "https://news.ycombinator.com/item?id=17514463",
"name": "Why You Hate Contemporary Architecture | Hacker News",
"dateAdd": "2018-07-14T09:12:20.196Z",
"dateUpdate": "2018-07-14T09:12:20.196Z",
"id": "f37fb625-066f-4240-a17d-02f02af2ae83",
"type": "url",
"tags": [ "articles / videos", "2017", ] ,
"images": [],
"description": ""
},{
"url": "https://hpi.de/en/baudisch/projects/trussfab.html",
"name": "TrussFab",
"dateAdd": "2018-07-24T04:04:15.262Z",
"dateUpdate": "2018-07-24T04:04:15.262Z",
"id": "bc903a5d-4fe4-4345-b8d6-198527d36d39",
"type": "url",
"tags": [ "articles / videos", "2017", ] ,
"images": [],
"description": ""
},{
"url": "https://habrahabr.info/development/open-source/3028-how-to-do-everything-yourself-open-modular-systems.html",
"name": "How to do everything yourself: open modular systems - HabraHabr.Info",
"dateAdd": "2018-07-21T20:21:34.924Z",
"dateUpdate": "2018-07-23T08:35:55.661Z",
"id": "5d6f9ece-4ca0-4809-8500-fe87e9059342",
"type": "url",
"tags": [ "articles / videos", "2018", ] ,
"images": [],
"description": ""
},{
"url": "https://feedyeti.com/hashtag.php?q=OpenStructures",
"name": "OpenStructures on FeedYeti.com",
"dateAdd": "2018-07-21T20:26:31.783Z",
"dateUpdate": "2018-07-21T20:26:31.784Z",
"id": "5259e175-4b1a-43a6-9003-13595867a071",
"type": "url",
"tags": [ "articles / videos", "2018", ] ,
"images": [],
"description": ""
},{
"url": "https://science.slashdot.org/story/18/05/04/1436238/can-we-live-without-concrete",
"name": "Can We Live Without Concrete? - Slashdot",
"dateAdd": "2018-05-05T06:50:15.000Z",
"dateUpdate": "2018-07-24T03:49:39.104Z",
"id": "5439c10e-7158-4242-a748-0681b850e513",
"type": "url",
"tags": [ "articles / videos", "2018", ] ,
"images": [],
"description": ""
},{
"url": "https://www.citylab.com/design/2018/06/can-silicon-valley-disrupt-how-we-build/562334/",
"name": "Why Silicon Valley Wants to Conquer Construction - CityLab",
"dateAdd": "2018-07-08T04:13:37.815Z",
"dateUpdate": "2019-03-02T10:25:25.147Z",
"id": "06184be0-64c5-4e34-a78d-2d50932c374a",
"type": "url",
"tags": [ "articles / videos", "2018", ] ,
"images": [],
"description": ""
},{
"url": "https://jods.mitpress.mit.edu/pub/issue3-brand",
"name": "Pace Layering: How Complex Systems Learn and Keep Learning",
"dateAdd": "2018-07-08T08:04:55.813Z",
"dateUpdate": "2018-07-24T04:05:09.155Z",
"id": "5f69cf65-8b03-4ea2-a84b-734eaf64d4ca",
"type": "url",
"tags": [ "articles / videos", "2018", "mit" ] ,
"images": [],
"description": ""
},{
"url": "http://www.keanw.com/2018/03/the-future-of-autocad.html",
"name": "The future of AutoCAD - Through the Interface",
"dateAdd": "2018-05-25T08:28:43.000Z",
"dateUpdate": "2018-07-24T04:31:04.289Z",
"id": "a95132d0-2cb2-4215-95db-6423dbc48267",
"type": "url",
"tags": [ "articles / videos", "2018", ] ,
"images": [],
"description": ""
},{
"url": "https://news.ycombinator.com/item?id=17133418",
"name": "The future of AutoCAD | Hacker News",
"dateAdd": "2018-05-25T08:35:59.000Z",
"dateUpdate": "",
"id": "40eb305f-9efc-4919-b939-8a9bf02723c6",
"type": "url",
"tags": [ "articles / videos", "2018", ] ,
"images": [],
"description": ""
},{
"url": "http://www.opensourcealternative.org/alternatives/graphic-editors/open-source-alternative-to-autocad/",
"name": "Open Source Alternative to AutoCAD | Open Source Alternative",
"dateAdd": "2017-12-31T19:33:16.000Z",
"dateUpdate": "2018-07-24T04:35:16.215Z",
"id": "74e79a46-2c28-4644-b0fa-03bca1be7851",
"type": "url",
"tags": [ "articles / videos", "2018", ] ,
"images": [],
"description": ""
},{
"url": "http://www.aecbytes.com/index.html",
"name": "AECbytes: Analysis, Research, and Reviews of AEC Technology",
"dateAdd": "2017-12-31T07:13:31.000Z",
"dateUpdate": "2019-03-02T08:10:36.297Z",
"id": "6a929741-e0ca-4152-aa28-1f8ecdf19399",
"type": "url",
"tags": [ "bim", ] ,
"images": [],
"description": ""
},{
"url": "http://bimwiki.com/",
"name": "BIM Wiki - BIM Wiki",
"dateAdd": "2017-12-31T07:13:31.000Z",
"dateUpdate": "2019-03-02T09:27:07.593Z",
"id": "d8bac36a-26b2-4f67-87fe-f8c097242200",
"type": "url",
"tags": [ "bim", ] ,
"images": [],
"description": ""
},{
"url": "http://www.stress-free.co.nz/bimserver_and_the_potential_of_serverside_bim",
"name": "BIMserver and the potential of server-side BIM | StressFree | David Harrison",
"dateAdd": "2017-12-31T07:13:31.000Z",
"dateUpdate": "",
"id": "068e7495-4973-4c2a-8b2f-e4f335755f79",
"type": "url",
"tags": [ "bim", ] ,
"images": [],
"description": ""
},{
"url": "http://bimserver.org/",
"name": "Bimserver.org",
"dateAdd": "2017-12-31T07:13:31.000Z",
"dateUpdate": "2019-03-02T09:25:50.556Z",
"id": "eef412d3-0cbc-4301-8686-ceefd2bace3d",
"type": "url",
"tags": [ "bim", ] ,
"images": [],
"description": ""
},{
"url": "http://bimstorm.com/i/WatchBimStorm.php",
"name": "BIMStorm - Watch",
"dateAdd": "2017-12-31T07:13:31.000Z",
"dateUpdate": "",
"id": "a1d1b946-590d-4b9a-96a9-40689cb0840c",
"type": "url",
"tags": [ "bim", ] ,
"images": [],
"description": ""
},{
"url": "http://bimsurfer.org/",
"name": "BIMsurfer WebGL viewer | Just another The smartBIM network site",
"dateAdd": "2017-12-31T07:13:31.000Z",
"dateUpdate": "2019-03-17T21:33:32.743Z",
"id": "52e31cad-fd83-4f95-8a2a-76785605b274",
"type": "url",
"tags": [ "bim", ] ,
"images": [],
"description": ""
},{
"url": "http://schemas.opengis.net/citygml/",
"name": "Index of /citygml",
"dateAdd": "2017-12-31T07:13:31.000Z",
"dateUpdate": "",
"id": "21e524b5-bf9d-4c20-8de9-74f76282c0aa",
"type": "url",
"tags": [ "bim", ] ,
"images": [],
"description": ""
},{
"url": "http://en.wikipedia.org/wiki/Industry_Foundation_Classes",
"name": "Industry Foundation Classes - Wikipedia, the free encyclopedia",
"dateAdd": "2017-12-31T07:13:31.000Z",
"dateUpdate": "",
"id": "57f860a4-68f2-4289-8463-27a06bed21a8",
"type": "url",
"tags": [ "bim", "wikipedia" ] ,
"images": [],
"description": ""
},{
"url": "http://www.wbdg.org/references/jbim.php",
"name": "Journal of Building Information Modeling | Whole Building Design Guide",
"dateAdd": "2017-12-31T07:13:31.000Z",
"dateUpdate": "2019-02-16T03:04:48.203Z",
"id": "b3192eb2-6654-4e5d-9b72-19c5a799b956",
"type": "url",
"tags": [ "bim", ] ,
"images": [],
"description": ""
},{
"url": "http://buildingsmart.com/standards/ifc",
"name": "Model - Industry Foundation Classes (IFC) — buildingSMART",
"dateAdd": "2017-12-31T07:13:31.000Z",
"dateUpdate": "2019-03-02T09:34:53.196Z",
"id": "dc23ce66-80e7-4dcf-b161-62b22e47e1f9",
"type": "url",
"tags": [ "bim", ] ,
"images": [],
"description": ""
},{
"url": "http://www.reedconstructiondata.com/bim/bim-library/",
"name": "SmartBIM Library for Autodesk Revit | SmartBIM | Reed Construction Data",
"dateAdd": "2017-12-31T07:13:31.000Z",
"dateUpdate": "",
"id": "08d62043-7213-44c5-9165-e200a298616c",
"type": "url",
"tags": [ "bim", ] ,
"images": [],
"description": ""
},{
"url": "http://www.solibri.com/",
"name": "Solibri",
"dateAdd": "2017-12-31T07:13:31.000Z",
"dateUpdate": "",
"id": "c53d2d06-636d-4a59-9026-eec511b48974",
"type": "url",
"tags": [ "bim", ] ,
"images": [],
"description": ""
},{
"url": "http://www.teklabimsight.com/index.jsp",
"name": "Tekla BIMsight Home page",
"dateAdd": "2017-12-31T07:13:31.000Z",
"dateUpdate": "2019-03-02T10:05:19.818Z",
"id": "9d6bae8c-e7ee-401e-8f7f-6f812fd899c1",
"type": "url",
"tags": [ "bim", ] ,
"images": [],
"description": ""
},{
"url": "http://www.whitefeet.com/",
"name": "WhiteFeet",
"dateAdd": "2017-12-31T07:13:31.000Z",
"dateUpdate": "2019-03-02T09:59:08.805Z",
"id": "7f9cf4b3-260f-458f-946e-ca8e06fa76ad",
"type": "url",
"tags": [ "bim", ] ,
"images": [],
"description": ""
},{
"url": "https://almond.stanford.edu/thingpedia",
"name": "Thingpedia - The Open API Collection",
"dateAdd": "2018-07-18T08:54:21.855Z",
"dateUpdate": "2019-03-25T02:53:08.794Z",
"id": "b8f94afb-71ce-4918-b653-c29f4fcc5bd5",
"type": "url",
"tags": [ "collaborating", ] ,
"images": [],
"description": ""
},{
"url": "https://mobisocial.stanford.edu/",
"name": "Stanford MobiSocial Computing Laboratory",
"dateAdd": "2018-07-18T08:58:26.693Z",
"dateUpdate": "2019-03-25T02:45:12.646Z",
"id": "851c5815-818d-462a-a3c9-71078ee9b447",
"type": "url",
"tags": [ "collaborating", ] ,
"images": [],
"description": ""
},{
"url": "https://news.ycombinator.com/item?id=17532003",
"name": "Almond – The Open Virtual Assistant | Hacker News",
"dateAdd": "2018-07-18T08:56:03.253Z",
"dateUpdate": "2019-02-10T00:33:57.624Z",
"id": "db4802a9-e9cf-4a23-9352-747c3bc6c6ef",
"type": "url",
"tags": [ "collaborating", ] ,
"images": [],
"description": ""
},{
"url": "https://almond.stanford.edu/",
"name": "Almond - The Open Virtual Assistant",
"dateAdd": "2018-07-18T08:54:13.878Z",
"dateUpdate": "2019-04-14T08:07:23.914Z",
"id": "a2ee34fd-e69c-419d-87ec-18c44b8f0f6f",
"type": "url",
"tags": [ "collaborating", ] ,
"images": [],
"description": ""
},{
"url": "https://medium.freecodecamp.org/how-to-write-a-good-software-design-document-66fcf019569c",
"name": "How to write a good software design doc – freeCodeCamp",
"dateAdd": "2018-07-18T09:16:26.194Z",
"dateUpdate": "2019-03-02T09:49:38.460Z",
"id": "d5e539b4-47ac-4ee3-a8cf-8c3a16d57285",
"type": "url",
"tags": [ "collaborating", ] ,
"images": [],
"description": ""
},{
"url": "https://espas.secure.europarl.europa.eu/orbis/sites/default/files/generated/document/en/10%20EFFLA%20Study%20-%20Tikka%20-%20Wevolve%20-%20Life%20styles.pdf",
"name": "EU2020_Digital",
"dateAdd": "2018-07-21T21:22:48.766Z",
"dateUpdate": "2018-07-21T21:24:31.561Z",
"id": "29137c6c-4b4d-4795-82ce-35a1277b38b4",
"type": "url",
"tags": [ "collaborating", "wevolve.us", ] ,
"images": [],
"description": ""
},{
"url": "https://wevolve.us/Approach",
"name": "Approach - Wevolve",
"dateAdd": "2018-07-21T21:23:02.422Z",
"dateUpdate": "2019-03-25T02:17:58.959Z",
"id": "4ac1a16e-1790-4a90-aa6a-d7d05e5aad89",
"type": "url",
"tags": [ "collaborating", "wevolve.us", ] ,
"images": [],
"description": ""
},{
"url": "https://wevolve.us/Infinite-orgs",
"name": "Infinite orgs - Wevolve",
"dateAdd": "2018-07-21T21:25:32.587Z",
"dateUpdate": "2018-11-26T06:02:35.535Z",
"id": "9af82516-5d93-46c3-bb6c-a5b25884de45",
"type": "url",
"tags": [ "collaborating", "wevolve.us", ] ,
"images": [],
"description": ""
},{
"url": "https://dynamicland.org/",
"name": "Dynamicland",
"dateAdd": "2017-12-31T07:13:28.000Z",
"dateUpdate": "2019-03-25T03:04:37.055Z",
"id": "5fa33ad4-1dcc-43f0-8464-36d292c42d0e",
"type": "url",
"tags": [ "collaborating", "wevolve.us", ] ,
"images": [],
"description": ""
},{
"url": "https://github.com/speckleworks/speckleworks.github.io",
"name": "speckleworks/speckleworks.github.io: the speckleworks website 🌍",
"dateAdd": "2018-08-03T22:42:32.883Z",
"dateUpdate": "2019-02-03T04:47:49.057Z",
"id": "92335ce8-bf53-4fbe-915d-5cb7fc0c6920",
"type": "url",
"tags": [ "collaborating", "wevolve.us", ] ,
"images": [],
"description": ""
},{
"url": "https://speckle.works/log/versionone/",
"name": "Speckle 1.0.0",
"dateAdd": "2018-08-03T23:39:14.285Z",
"dateUpdate": "2018-08-03T23:39:14.287Z",
"id": "a814e57a-9a5c-4f25-8cc5-57945e947037",
"type": "url",
"tags": [ "collaborating", "wevolve.us", ] ,
"images": [],
"description": ""
},{
"url": "https://opencollective.com/",
"name": "Home - Open Collective",
"dateAdd": "2018-08-04T19:07:36.473Z",
"dateUpdate": "2019-03-25T03:09:05.513Z",
"id": "b196831b-15e1-4d20-bd10-997e3ed01c73",
"type": "url",
"tags": [ "collaborating", "wevolve.us", ] ,
"images": [],
"description": ""
},{
"url": "https://www.configura.com/",
"name": "Design spaces - Configuration made simple | Configura",
"dateAdd": "2018-07-24T04:27:14.107Z",
"dateUpdate": "2018-07-24T04:27:14.107Z",
"id": "95748010-9903-44cb-a6a3-b8ca993d134f",
"type": "url",
"tags": [ "configurators", ] ,
"images": [],
"description": ""
},{
"url": "https://www.bluhomes.com/design_studio/",
"name": "Unity WebGL Player | Blu Design Studio",
"dateAdd": "2018-07-24T04:27:24.503Z",
"dateUpdate": "2018-07-24T04:27:24.504Z",
"id": "a425b30e-4286-4904-a0af-a033b67f30f1",
"type": "url",
"tags": [ "configurators", ] ,
"images": [],
"description": ""
},{
"url": "https://www.configura.com/",
"name": "Design spaces - Configuration made simple | Configura",
"dateAdd": "2018-07-19T07:55:43.801Z",
"dateUpdate": "2018-07-24T04:27:14.107Z",
"id": "5705c5cb-5d43-4f61-b603-707f1f389394",
"type": "url",
"tags": [ "configurators", ] ,
"images": [],
"description": ""
},{
"url": "https://archilogic.com/",
"name": "Professional Floor Plans To Showcase Your Space | Archilogic",
"dateAdd": "2018-07-24T04:31:31.525Z",
"dateUpdate": "2019-03-02T09:06:47.947Z",
"id": "2f41619c-de42-4379-a380-79494d33f2b6",
"type": "url",
"tags": [ "design tools", "archilogic", ] ,
"images": [],
"description": ""
},{
"url": "https://3d.io/#pricing",
"name": "3d.io",
"dateAdd": "2018-07-24T04:35:02.789Z",
"dateUpdate": "2018-07-24T04:35:02.790Z",
"id": "c1cf741f-0077-419c-8748-b7ee43aeff5a",
"type": "url",
"tags": [ "design tools", "archilogic", ] ,
"images": [],
"description": ""
},{
"url": "https://archilogic.com/",
"name": "Professional Floor Plans To Showcase Your Space | Archilogic",
"dateAdd": "2018-07-19T07:51:28.269Z",
"dateUpdate": "2019-03-02T09:06:47.947Z",
"id": "03ef728d-5e5f-42ec-a4a1-2733b6dbe4b4",
"type": "url",
"tags": [ "design tools", "archilogic", ] ,
"images": [],
"description": ""
},{
"url": "https://3d.io/",
"name": "3d.io",
"dateAdd": "2018-07-19T07:51:48.552Z",
"dateUpdate": "2019-04-08T05:55:56.891Z",
"id": "e49fed8a-714f-4b8d-adb7-7a249a41bdc3",
"type": "url",
"tags": [ "design tools", "archilogic", ] ,
"images": [],
"description": ""
},{
"url": "https://www.autodesk.com/products/autocad/overview",
"name": "AutoCAD For Mac & Windows | CAD Software | Autodesk",
"dateAdd": "2018-07-19T07:51:16.501Z",
"dateUpdate": "2018-07-19T07:51:16.501Z",
"id": "59dfa80a-217f-4251-ac18-e9959c695d8d",
"type": "url",
"tags": [ "design tools", "autodesk", ] ,
"images": [],
"description": ""
},{
"url": "http://build.slashdot.org/story/15/07/27/1816234/you3dit-is-working-to-help-crowdsource-3d-design-and-printing-video",
"name": "You3dit is Working to Help Crowdsource 3D Design and Printing (Video) - Slashdot",
"dateAdd": "2017-12-31T19:33:28.000Z",
"dateUpdate": "2018-07-21T09:49:28.096Z",
"id": "e3b1bb16-012f-4578-8f15-c50ec3c4dbd2",
"type": "url",
"tags": [ "design tools", "design-3d", ] ,
"images": [],
"description": ""
},{
"url": "http://solvespace.com/index.pl",
"name": "SolveSpace - parametric 3d CAD",
"dateAdd": "2017-12-31T19:33:28.000Z",
"dateUpdate": "2018-07-21T08:46:13.296Z",
"id": "e0c09d66-3899-404a-87f4-729eeaaae4ba",
"type": "url",
"tags": [ "design tools", "design-3d", ] ,
"images": [],
"description": ""
},{
"url": "http://bits.blogs.nytimes.com/2015/02/15/slice-and-carve-the-next-wave-in-computer-aided-creativity/?_r=1",
"name": "Slice and Carve: The Next Wave in Computer-Aided Creativity - NYTimes.com",
"dateAdd": "2017-12-31T19:33:28.000Z",
"dateUpdate": "",
"id": "99b37ad5-f7bb-4ee4-939e-eea714f6af17",
"type": "url",
"tags": [ "design tools", "design-3d", ] ,
"images": [],
"description": ""
},{
"url": "http://lumion3d.com/",
"name": "Lumion 3D - Architectural Visualization Software",
"dateAdd": "2017-12-31T19:33:28.000Z",
"dateUpdate": "2018-07-19T08:28:06.625Z",
"id": "3b1916b0-8027-4d61-bfb7-175f748616a3",
"type": "url",
"tags": [ "design tools", "design-3d", ] ,
"images": [],
"description": ""
},{
"url": "http://jscottk.itch.io/graffiti-3d",
"name": "Graffiti 3D by jscottk",
"dateAdd": "2017-12-31T19:33:28.000Z",
"dateUpdate": "2018-07-19T08:28:09.673Z",
"id": "348c75d5-33a0-4854-9db0-51ae2a499815",
"type": "url",
"tags": [ "design tools", "design-3d", ] ,
"images": [],
"description": ""
},{
"url": "http://omrelli.ug/g9/gallery/",
"name": "g9 Gallery | Automatically Interactive Graphics",
"dateAdd": "2017-12-31T19:33:28.000Z",
"dateUpdate": "2019-03-02T10:15:50.177Z",
"id": "c12dffcc-fa0c-49d7-82a5-f472c04a1e3d",
"type": "url",
"tags": [ "design tools", "design-3d", ] ,
"images": [],
"description": ""
},{
"url": "http://beetleblocks.com/run/",
"name": "BeetleBlocks",
"dateAdd": "2017-12-31T19:33:28.000Z",
"dateUpdate": "2019-04-14T08:13:30.561Z",
"id": "f3d66daa-5acf-4387-a425-e05fb0002fd2",
"type": "url",
"tags": [ "design tools", "design-3d", ] ,
"images": [],
"description": ""
},{
"url": "http://stephaneginier.com/",
"name": "Homepage",
"dateAdd": "2017-12-31T19:33:28.000Z",
"dateUpdate": "2018-07-19T08:28:20.723Z",
"id": "37b707c8-d819-4b33-aa4f-4c8bf29d3da2",
"type": "url",
"tags": [ "design tools", "design-3d", ] ,
"images": [],
"description": ""
},{
"url": "https://www.sketchup.com/",
"name": "3D modeling for everyone | SketchUp",
"dateAdd": "2018-07-19T07:46:28.472Z",
"dateUpdate": "2018-07-19T07:46:28.472Z",
"id": "2ec7c13d-cd9b-468c-9bc1-30b40bb4d73c",
"type": "url",
"tags": [ "design tools", "sketchup", ] ,
"images": [],
"description": ""
},{
"url": "http://www.spacegoo.com/lignum/index.php?constructor=Demo1",
"name": ".: L I G N U M :.",
"dateAdd": "2018-07-24T04:28:47.490Z",
"dateUpdate": "2018-07-24T04:28:47.490Z",
"id": "4e993726-9b7b-47fc-a111-4ac81fd6e2ff",
"type": "url",
"tags": [ "design tools", "spacegoo", ] ,
"images": [],
"description": ""
},{
"url": "https://docs.google.com/document/d/1JyTvTgsJQmUJKG-dJdRMxJxGxQozlLp0wMrHKjghDg4/edit#heading=h.38q9ui7hklli",
"name": "TrussFab users manual - Google Docs",
"dateAdd": "2018-07-24T04:00:38.441Z",
"dateUpdate": "2018-07-24T04:00:38.442Z",
"id": "e7dcc429-cfea-4639-a45f-db5efcfafcfe",
"type": "url",
"tags": [ "design tools", "trussfab", ] ,
"images": [],
"description": ""
},{
"url": "https://hpi.de/en/baudisch/projects/trussfab.html",
"name": "TrussFab",
"dateAdd": "2018-07-24T04:01:03.970Z",
"dateUpdate": "2018-07-24T04:04:15.262Z",
"id": "4719c0e1-5ff4-436e-99fb-f5d0cd65d693",
"type": "url",
"tags": [ "design tools", "trussfab", ] ,
"images": [],
"description": ""
},{
"url": "https://dl.acm.org/citation.cfm?id=3026016",
"name": "TrussFab",
"dateAdd": "2018-07-24T04:01:56.196Z",
"dateUpdate": "2019-04-14T08:39:10.333Z",
"id": "8ff6e194-e520-4402-b696-0784faf79353",
"type": "url",
"tags": [ "design tools", "trussfab", ] ,
"images": [],
"description": ""
},{
"url": "https://savage.nps.edu/X3D-Edit/#Features",
"name": "/X3D-Edit/#Features",
"dateAdd": "2017-12-31T07:13:31.000Z",
"dateUpdate": "",
"id": "f225051a-1786-4b32-96e5-dc80d11c13d1",
"type": "url",
"tags": [ "design tools", "trussfab", ] ,
"images": [],
"description": ""
},{
"url": "http://beetleblocks.com/run/",
"name": "Beetle Blocks editor",
"dateAdd": "2018-07-19T08:31:04.638Z",
"dateUpdate": "2019-04-14T08:13:30.561Z",
"id": "b1bcabeb-05b8-45a6-87e1-c3d984d0e81a",
"type": "url",
"tags": [ "design tools", "trussfab", ] ,
"images": [],
"description": ""
},{
"url": "https://lumion.com/",
"name": "Fast Rendering for Architects | Lumion",
"dateAdd": "2018-07-19T08:29:50.563Z",
"dateUpdate": "2018-07-19T08:29:50.563Z",
"id": "deeebef0-250b-4f24-820e-a14784e59352",
"type": "url",
"tags": [ "design tools", "trussfab", ] ,
"images": [],
"description": ""
},{
"url": "http://www.floored.com/homepage/",
"name": "Floored",
"dateAdd": "2018-07-24T04:28:15.373Z",
"dateUpdate": "2018-07-24T04:53:12.696Z",
"id": "4fd085df-fcbc-439b-8abb-7f6fc57609d9",
"type": "url",
"tags": [ "design tools", "trussfab", ] ,
"images": [],
"description": ""
},{
"url": "https://jscottk.itch.io/graffiti-3d",
"name": "Graffiti 3D by jscottk",
"dateAdd": "2018-07-19T08:30:07.594Z",
"dateUpdate": "2018-07-24T04:54:24.373Z",
"id": "c946e3da-07ec-4e87-b0eb-cec8526169af",
"type": "url",
"tags": [ "design tools", "trussfab", ] ,
"images": [],
"description": ""
},{
"url": "https://www.ladybug.tools/",
"name": "Ladybug Tools | Home Page",
"dateAdd": "2018-07-19T07:48:25.970Z",
"dateUpdate": "2019-05-17T19:06:06.144Z",
"id": "e9d7b02c-3785-4416-884e-93874372ccdd",
"type": "url",
"tags": [ "design tools", "trussfab", ] ,
"images": [],
"description": ""
},{
"url": "http://www.open3mod.com/",
"name": "Open 3D Model Viewer",
"dateAdd": "2017-12-31T19:33:48.000Z",
"dateUpdate": "2018-07-21T08:57:51.602Z",
"id": "ddc8e131-e9c6-4618-8187-6b9cb27ae3be",
"type": "url",
"tags": [ "design tools", "trussfab", ] ,
"images": [],
"description": ""
},{
"url": "https://stephaneginier.com/sculptgl/",
"name": "SculptGL - A WebGL sculpting app",
"dateAdd": "2018-07-24T04:37:23.246Z",
"dateUpdate": "2018-07-24T04:37:23.247Z",
"id": "6fea20e9-cb9b-4d2c-a7e9-98d42e0f1769",
"type": "url",
"tags": [ "design tools", "trussfab", ] ,
"images": [],
"description": ""
},{
"url": "http://shapesmith.net/",
"name": "Shapesmith.net",
"dateAdd": "2018-07-19T08:25:52.546Z",
"dateUpdate": "2018-07-21T09:05:40.631Z",
"id": "dd830788-a9db-4357-9d92-a7a45e0ee1e5",
"type": "url",
"tags": [ "design tools", "trussfab", "mit" ] ,
"images": [],
"description": ""
},{
"url": "http://www.sketchthis.net/",
"name": "SketchThis.NET",
"dateAdd": "2018-07-19T08:20:17.806Z",
"dateUpdate": "2018-07-19T08:20:17.807Z",
"id": "c1b20460-a02d-4130-8bc8-cbee3f222f50",
"type": "url",
"tags": [ "design tools", "trussfab", ] ,
"images": [],
"description": ""
},{
"url": "http://solvespace.com/index.pl",
"name": "SolveSpace - parametric 3d CAD",
"dateAdd": "2018-07-19T08:27:52.829Z",
"dateUpdate": "2018-07-21T08:46:13.296Z",
"id": "6a743d42-eca6-4963-ace5-6dd1854088e6",
"type": "url",
"tags": [ "design tools", "trussfab", ] ,
"images": [],
"description": ""
},{
"url": "http://www.floored.com/homepage/",
"name": "Floored",
"dateAdd": "2018-07-19T07:54:06.784Z",
"dateUpdate": "2018-07-24T04:53:12.696Z",
"id": "d65d3eed-26be-4c0f-91d7-e4910240de9f",
"type": "url",
"tags": [ "design tools", "trussfab", ] ,
"images": [],
"description": ""
},{
"url": "http://www.openstructures.net/",
"name": "OS - OpenStructures",
"dateAdd": "2018-07-21T19:48:30.408Z",
"dateUpdate": "2019-03-03T01:29:18.575Z",
"id": "c37cd353-2b78-4db6-ae5e-1dc4cc5ff1b3",
"type": "url",
"tags": [ "designers", "OpenStructures", ] ,
"images": [],
"description": ""
},{
"url": "http://beta.openstructures.net/",
"name": "Home.",
"dateAdd": "2018-07-21T20:03:01.746Z",
"dateUpdate": "2019-03-03T01:30:26.016Z",
"id": "72c8fc6c-c7d6-4e4a-a855-8c9a7e0803ae",
"type": "url",
"tags": [ "designers", "OpenStructures", ] ,
"images": [],
"description": ""
},{
"url": "https://en.wikipedia.org/wiki/OpenStructures",
"name": "OpenStructures - Wikipedia",
"dateAdd": "2018-07-21T20:03:33.845Z",
"dateUpdate": "2019-01-20T22:51:39.449Z",
"id": "87c54ae7-c339-4276-bc32-0862d8a540e3",
"type": "url",
"tags": [ "designers", "OpenStructures", "wikipedia" ] ,
"images": [],
"description": ""
},{
"url": "https://www.dezeen.com/2009/11/11/openstructures-by-thomas-lommee/",
"name": "OpenStructures by Thomas Lommée | Dezeen",
"dateAdd": "2018-07-21T19:48:42.651Z",
"dateUpdate": "2019-03-03T01:09:12.779Z",
"id": "f125aead-c659-4a64-b678-8fc6cf9f6738",
"type": "url",
"tags": [ "designers", "OpenStructures", "dezeen" ] ,
"images": [],
"description": ""
},{
"url": "https://wiki.p2pfoundation.net/Open_Structures_Project",
"name": "Open Structures Project - P2P Foundation",
"dateAdd": "2018-07-21T19:49:49.844Z",
"dateUpdate": "2018-07-21T19:49:49.845Z",
"id": "ac75c38b-7113-458a-a5d4-2bd2122dc779",
"type": "url",
"tags": [ "designers", "OpenStructures", ] ,
"images": [],
"description": ""
},{
"url": "http://www.contraptor.org/forum/t-273404/contraptor-openstructures",
"name": "Contraptor + Openstructures - Contraptor",
"dateAdd": "2018-07-21T19:51:58.697Z",
"dateUpdate": "2018-07-21T19:51:58.697Z",
"id": "6ee11c25-3070-44de-abae-6c54f3cee5a5",
"type": "url",
"tags": [ "designers", "OpenStructures", ] ,
"images": [],
"description": ""
},{
"url": "http://institutewithoutboundaries.ca/?portfolio=open-structures",
"name": "OpenStructures – Institute without Boundaries",
"dateAdd": "2018-07-21T20:04:06.012Z",
"dateUpdate": "2019-02-12T04:47:13.767Z",
"id": "3928e737-ab37-4215-9a81-6d8bc2707ce1",
"type": "url",
"tags": [ "designers", "OpenStructures", ] ,
"images": [],
"description": ""
},{
"url": "http://intrastructures.net/Intrastructures/Analysis_files/flyer_final-ENG.pdf",
"name": "flyer_final-ENG.pdf",
"dateAdd": "2018-07-21T19:56:16.914Z",
"dateUpdate": "2018-07-29T06:25:50.036Z",
"id": "17fa2108-69b1-4e37-88e1-d5ec7e34f6d9",
"type": "url",
"tags": [ "designers", "OpenStructures", ] ,
"images": [],
"description": ""
},{
"url": "https://frieze.com/article/lot-small-things",
"name": "A Lot of Small Things | Frieze",
"dateAdd": "2018-07-21T20:11:19.069Z",
"dateUpdate": "2018-07-21T20:14:09.978Z",
"id": "8dad6861-cc47-46a4-82ac-0f479b04a8ab",
"type": "url",
"tags": [ "designers", "OpenStructures", ] ,
"images": [],
"description": ""
},{
"url": "https://makezine.com/2010/02/23/open-structures-help-create-an-open/",
"name": "Open Structures: Help create an open-source building system",
"dateAdd": "2018-07-21T20:15:11.897Z",
"dateUpdate": "2019-02-12T04:44:48.034Z",
"id": "03071f0f-e65f-4059-875d-35d049b92372",
"type": "url",
"tags": [ "articles", "2010", ] ,
"images": [],
"description": ""
},{
"url": "https://frieze.com/article/lot-small-things",
"name": "A Lot of Small Things | Frieze",
"dateAdd": "2018-07-21T20:13:46.447Z",
"dateUpdate": "2018-07-21T20:14:09.978Z",
"id": "084531ff-7810-4d68-a3c3-89048b5d077b",
"type": "url",
"tags": [ "articles", "2012", ] ,
"images": [],
"description": ""
},{
"url": "http://www.lowtechmagazine.com/2012/12/how-to-make-everything-ourselves-open-modular-hardware.html",
"name": "How to Make Everything Ourselves: Open Modular Hardware - LOW-TECH MAGAZINE",
"dateAdd": "2018-07-23T08:35:39.397Z",
"dateUpdate": "2018-07-23T08:35:39.398Z",
"id": "da80c103-9d3e-4f01-b84d-b5e110c9e116",
"type": "url",
"tags": [ "articles", "2012", ] ,
"images": [],
"description": ""
},{
"url": "https://www.smow.com/blog/2016/02/smow-blog-interview-thomas-lommee-designers-job-generate-solutions/",
"name": "smow Blog Interview: Thomas Lommée - as designers our job is to generate solutions - smow Blog English",
"dateAdd": "2018-07-21T20:16:12.960Z",
"dateUpdate": "2018-07-21T20:16:12.961Z",
"id": "9ddbeb85-df90-49b0-a855-75456e33a3e8",
"type": "url",
"tags": [ "articles", "2016", ] ,
"images": [],
"description": ""
},{
"url": "https://ods.matera-basilicata2019.it/en/689-blog/principles/5803-openstructures",
"name": "OpenStructures",
"dateAdd": "2018-07-21T20:13:27.349Z",
"dateUpdate": "2019-02-12T04:46:40.703Z",
"id": "1b6e5196-47b8-46ae-8a00-2a3ee64a9024",
"type": "url",
"tags": [ "articles", "2017", ] ,
"images": [],
"description": ""
},{
"url": "https://twitter.com/hashtag/OpenStructures?src=hash&lang=en",
"name": "#OpenStructures hashtag on Twitter",
"dateAdd": "2018-07-21T20:17:32.340Z",
"dateUpdate": "2019-02-12T05:53:05.283Z",
"id": "27674553-c26e-4425-9cc3-cfcac7659aa7",
"type": "url",
"tags": [ "articles", "2017", ] ,
"images": [],
"description": ""
},{
"url": "http://institutewithoutboundaries.ca/?portfolio=open-structures",
"name": "OpenStructures – Institute without Boundaries",
"dateAdd": "2018-07-21T20:14:25.099Z",
"dateUpdate": "2019-02-12T04:47:13.767Z",
"id": "7e0e79ee-564f-48a3-8613-2150a09d1ac0",
"type": "url",
"tags": [ "articles", "2017", ] ,
"images": [],
"description": ""
},{
"url": "https://habrahabr.info/development/open-source/3028-how-to-do-everything-yourself-open-modular-systems.html",
"name": "How to do everything yourself: open modular systems - HabraHabr.Info",
"dateAdd": "2018-07-21T20:20:05.412Z",
"dateUpdate": "2018-07-23T08:35:55.661Z",
"id": "1684f321-c73e-4a18-979d-2eb9113b3bb4",
"type": "url",
"tags": [ "articles", "2018", ] ,
"images": [],
"description": ""
},{
"url": "https://wikihouse.cc/",
"name": "WikiHouse",
"dateAdd": "2018-07-19T07:37:21.861Z",
"dateUpdate": "2018-07-26T05:05:13.602Z",
"id": "17c0ca6d-40fb-4248-882a-2ed4a7d3e5e2",
"type": "url",
"tags": [ "designers", "wikihouse", ] ,
"images": [],
"description": ""
},{
"url": "https://harryknight.gitbooks.io/wikihouse-slack/content/",
"name": "Introduction · Communities Connect Guide",
"dateAdd": "2018-07-24T04:43:03.054Z",
"dateUpdate": "2018-07-24T04:43:03.055Z",
"id": "f02248cc-9550-47c6-8f97-59e9e9c0df4e",
"type": "url",
"tags": [ "designers", "wikihouse", ] ,
"images": [],
"description": ""
},{
"url": "http://wikihouse.github.io/viewer-experiments/",
"name": "WikiHouse Viewer Experiments",
"dateAdd": "2018-07-24T04:44:29.217Z",
"dateUpdate": "2018-07-24T04:44:29.218Z",
"id": "0a4f2f23-13b6-4208-b72d-77b592659b9f",
"type": "url",
"tags": [ "designers", "wikihouse", ] ,
"images": [],
"description": ""
},{
"url": "https://en.wikipedia.org/wiki/WikiHouse",
"name": "WikiHouse - Wikipedia",
"dateAdd": "2018-07-24T05:48:00.496Z",
"dateUpdate": "2018-07-24T05:48:00.496Z",
"id": "a9a2420e-b410-4237-84f5-d1939dc6ec89",
"type": "url",
"tags": [ "designers", "wikihouse", "wikipedia" ] ,
"images": [],
"description": ""
},{
"url": "http://www.spacegoo.com/",
"name": ".: SPACEGOO :.",
"dateAdd": "2018-07-19T07:53:38.877Z",
"dateUpdate": "2018-07-19T07:53:38.878Z",
"id": "50e8bbdd-4fdc-4655-8be1-641f47c4d59f",
"type": "url",
"tags": [ "designers", "wikihouse", ] ,
"images": [],
"description": ""
},{
"url": "http://www.weehouse.com/",
"name": "Alchemy Architects | Home of the weeHouse®",
"dateAdd": "2018-07-19T07:59:54.284Z",
"dateUpdate": "2018-07-24T04:23:35.330Z",
"id": "471e8910-4f9f-4951-be56-ef062f4ed078",
"type": "url",
"tags": [ "designers", "wikihouse", ] ,
"images": [],
"description": ""
},{
"url": "http://collectiveworks.net/",
"name": "Architecture & design studio built on collaboration • Collective Works",
"dateAdd": "2018-07-19T08:03:59.714Z",
"dateUpdate": "2018-07-24T04:53:57.110Z",
"id": "7e6f53ce-5da6-4766-9fd0-ef3156be8d29",
"type": "url",
"tags": [ "designers", "wikihouse", ] ,
"images": [],
"description": ""
},{
"url": "http://paperhouses.co/",
"name": "Home - Paperhouses",
"dateAdd": "2018-07-19T07:29:20.660Z",
"dateUpdate": "2018-07-24T04:53:28.570Z",
"id": "d32c95f6-58a9-4820-ae88-290f34c26688",
"type": "url",
"tags": [ "designers", "wikihouse", ] ,
"images": [],
"description": ""
},{
"url": "http://www.ideabox.us/",
"name": "ideabox",
"dateAdd": "2018-07-19T08:03:39.277Z",
"dateUpdate": "2018-07-24T04:21:58.836Z",
"id": "107b4474-c8d6-4cd9-94e0-5d366788610b",
"type": "url",
"tags": [ "designers", "wikihouse", ] ,
"images": [],
"description": ""
},{
"url": "https://www.plethora-project.com/",
"name": "Plethora Project",
"dateAdd": "2018-07-19T07:25:03.702Z",
"dateUpdate": "2018-07-24T04:49:21.463Z",
"id": "2a2e82cf-6edc-4ac4-a0db-eaf919d6eb2b",
"type": "url",
"tags": [ "designers", "wikihouse", "eth" ] ,
"images": [],
"description": ""
},{
"url": "http://www.architectsmart.com/",
"name": "Sam Marts Architects & Planners – The Art & Integration of Design & Construction",
"dateAdd": "2018-07-19T07:41:57.301Z",
"dateUpdate": "2019-03-02T09:12:59.629Z",
"id": "44205ded-2592-418c-a141-fc02a43c2ec4",
"type": "url",
"tags": [ "designers", "wikihouse", ] ,
"images": [],
"description": ""
},{
"url": "http://studies.bc-as.org/",
"name": "studies",
"dateAdd": "2018-07-07T07:09:15.528Z",
"dateUpdate": "2018-07-21T09:50:50.038Z",
"id": "b96eeae8-56ef-410d-b373-8849038f2fc6",
"type": "url",
"tags": [ "designers", "wikihouse", ] ,
"images": [],
"description": ""
},{
"url": "http://www.studioweave.com/",
"name": "Studio Weave",
"dateAdd": "2018-07-19T08:00:30.873Z",
"dateUpdate": "2018-07-24T04:23:33.499Z",
"id": "22d505d0-04d2-47b0-8ac9-28e0e4ed3cc3",
"type": "url",
"tags": [ "designers", "wikihouse", ] ,
"images": [],
"description": ""
},{
"url": "https://aetypic.com/",
"name": "The Best Architecture and Engineering Consulting Firm in San Francisco | Aetypic is an integrated design firm with 20+ consultants specialized in architecture, civil, structural engineering in San Francisco",
"dateAdd": "2018-07-19T08:05:19.096Z",
"dateUpdate": "2019-04-14T07:23:54.977Z",
"id": "619aa900-ffa2-44eb-af41-5271fcbae44f",
"type": "url",
"tags": [ "designers", "wikihouse", ] ,
"images": [],
"description": ""
},{
"url": "http://www.docstoc.com/documents/technology",
"name": "Find and share free technology documents - docstoc",
"dateAdd": "2017-12-31T19:33:50.000Z",
"dateUpdate": "",
"id": "1d3b93fe-2e9e-4f89-a7ba-407d1e430fe2",
"type": "url",
"tags": [ "documents technical", ] ,
"images": [],
"description": ""
},{
"url": "http://www.ibiblio.org/",
"name": "ibiblio - The Public's Library and Digital Archive",
"dateAdd": "2017-12-31T19:33:50.000Z",
"dateUpdate": "2019-03-02T10:21:35.705Z",
"id": "977474f5-bfb3-4819-8bbb-284a4eb986dd",
"type": "url",
"tags": [ "documents technical", ] ,
"images": [],
"description": ""
},{
"url": "http://www.wikibooks.org/",
"name": "Wikibooks",
"dateAdd": "2017-12-31T19:33:50.000Z",
"dateUpdate": "2019-03-02T09:58:30.655Z",
"id": "c3514155-9d9e-4b02-a972-eb35488bb5da",
"type": "url",
"tags": [ "documents technical", ] ,
"images": [],
"description": ""
},{
"url": "https://github.com/dortheimer/open-architecture",
"name": "dortheimer/open-architecture: Open Source license for Architecture and construction",
"dateAdd": "2018-07-20T08:44:25.700Z",
"dateUpdate": "2019-03-02T07:34:24.406Z",
"id": "e3433d38-4c9a-4989-865a-75282f7b5a6c",
"type": "url",
"tags": [ "intellectual property", ] ,
"images": [],
"description": ""
},{
"url": "https://www.lego.com/en-us/life",
"name": "LEGO® Life",
"dateAdd": "2018-07-24T06:47:41.167Z",
"dateUpdate": "2018-07-24T06:47:41.168Z",
"id": "550e82a4-cfa8-4b20-b826-968326857214",
"type": "url",
"tags": [ "lego", ] ,
"images": [],
"description": ""
},{
"url": "https://3dwarehouse.sketchup.com/model/5d041dd10944d3b570d45c28bef72613/LEGO?hl=en",
"name": "LEGO | 3D Warehouse",
"dateAdd": "2018-07-24T06:48:40.214Z",
"dateUpdate": "2019-04-14T06:43:01.340Z",
"id": "bf4750a1-7eb7-4544-8265-1bb329bc7386",
"type": "url",
"tags": [ "lego", ] ,
"images": [],
"description": ""
},{
"url": "https://printabrick.org/",
"name": "PrintABrick - Web catalogue of LEGO® parts for 3D printing",
"dateAdd": "2018-07-24T06:49:46.279Z",
"dateUpdate": "2018-07-24T06:49:46.280Z",
"id": "79bacaee-884b-4ed9-9c03-e1c54a3c3fd1",
"type": "url",
"tags": [ "lego", ] ,
"images": [],
"description": ""
},{
"url": "https://www.thingiverse.com/thing:2411971",
"name": "Print a Brick: All LEGO® parts and sets by hroncok - Thingiverse",
"dateAdd": "2018-07-24T06:51:25.605Z",
"dateUpdate": "2018-07-24T06:51:25.605Z",
"id": "88400de6-27ef-4a1b-9a4f-df51c48f9cb0",
"type": "url",
"tags": [ "lego", ] ,
"images": [],
"description": ""
},{
"url": "https://sploid.gizmodo.com/super-sizing-lego-sets-is-the-only-reason-you-need-a-3d-1798494911",
"name": "Super-Sizing Lego Sets Is the Only Reason You Need a 3D Printer",
"dateAdd": "2018-07-24T06:51:31.670Z",
"dateUpdate": "2018-07-24T06:51:31.670Z",
"id": "b27b64f8-59a6-420f-8117-354724dfe35d",
"type": "url",
"tags": [ "lego", ] ,
"images": [],
"description": ""
},{
"url": "https://sketchfab.com/tags/lego",
"name": "3D models tagged lego - Sketchfab",
"dateAdd": "2018-07-24T06:53:51.567Z",
"dateUpdate": "2018-07-24T06:53:51.567Z",
"id": "75fd170c-5d69-4a1a-bf8e-7da0073624e2",
"type": "url",
"tags": [ "lego", ] ,
"images": [],
"description": ""
},{
"url": "https://www.buildwithchrome.com/",
"name": "Build with Chrome",
"dateAdd": "2018-07-24T06:54:17.171Z",
"dateUpdate": "2018-07-24T07:06:01.773Z",
"id": "d34bf5a9-dffb-4820-8659-5e5f290e8bdf",
"type": "url",
"tags": [ "lego", ] ,
"images": [],
"description": ""
},{
"url": "http://www.drububu.com/miscellaneous/legolizer/index.html",
"name": "legolizer, custom lego objects",
"dateAdd": "2018-07-24T06:57:56.272Z",
"dateUpdate": "2018-07-24T06:57:56.273Z",
"id": "cc771d55-62db-4f56-8824-8cd1d1e15869",
"type": "url",
"tags": [ "lego", ] ,
"images": [],
"description": ""
},{
"url": "https://www.leocad.org/",
"name": "LeoCAD - Virtual LEGO CAD Software",
"dateAdd": "2018-07-24T07:00:40.499Z",
"dateUpdate": "2018-07-24T07:00:40.499Z",
"id": "9dd8719e-c670-4392-96ec-cc7f0368c3b7",
"type": "url",
"tags": [ "lego", ] ,
"images": [],
"description": ""
},{
"url": "http://www.ldraw.org/",
"name": "LDraw.org - Home",
"dateAdd": "2018-07-24T07:01:34.649Z",
"dateUpdate": "2018-07-24T07:01:34.649Z",
"id": "22a9151b-7b69-44aa-bd0a-bd395a170032",
"type": "url",
"tags": [ "lego", ] ,
"images": [],
"description": ""
},{
"url": "https://studio.bricklink.com/v2/build/studio.page",
"name": "BrickLink - Studio",
"dateAdd": "2018-07-24T07:03:35.753Z",
"dateUpdate": "2018-07-29T06:33:20.162Z",
"id": "f012828e-5f30-495f-9161-70ee61f07ba5",
"type": "url",
"tags": [ "lego", ] ,
"images": [],
"description": ""
},{
"url": "https://www.techsupportalert.com/content/best-free-lego-building-program.htm",
"name": "Best Free Lego Building Software | Gizmo's Freeware",
"dateAdd": "2018-07-24T07:04:00.958Z",
"dateUpdate": "2019-03-02T10:06:27.925Z",
"id": "75fbc5d3-45db-47d0-8da0-fd7978cb8642",
"type": "url",
"tags": [ "lego", ] ,
"images": [],
"description": ""
},{
"url": "https://www.mecabricks.com/en/workshop",
"name": "Mecabricks.com | Workshop",
"dateAdd": "2018-07-24T07:05:38.128Z",
"dateUpdate": "2019-03-02T09:53:20.407Z",
"id": "195cc0ea-cfd0-4ac1-922b-de397364708c",
"type": "url",
"tags": [ "lego", ] ,
"images": [],
"description": ""
},{
"url": "https://www.tinkercad.com/bricks",
"name": "Brickify your 3D designs | Tinkercad",
"dateAdd": "2018-07-24T07:06:31.655Z",
"dateUpdate": "2018-07-24T07:06:31.655Z",
"id": "2e4914aa-c19d-470d-9d38-5afc0ba549b6",
"type": "url",
"tags": [ "lego", ] ,
"images": [],
"description": ""
},{
"url": "https://github.com/adius/awesome-lego",
"name": "adius/awesome-lego: Curated list of awesome LEGO resources",
"dateAdd": "2018-07-24T07:08:07.877Z",
"dateUpdate": "2018-07-24T07:08:37.415Z",
"id": "f14ac3a4-faea-4796-b6f5-9ab5fa6d940d",
"type": "url",
"tags": [ "lego", ] ,
"images": [],
"description": ""
},{
"url": "https://opensource.com/life/15/11/8-open-source-lego-projects",
"name": "8 open source LEGO projects | Opensource.com",
"dateAdd": "2018-07-24T07:09:06.672Z",
"dateUpdate": "2018-07-24T07:09:06.673Z",
"id": "b2670515-aa6f-4cf4-b84a-1b1eef5a3110",
"type": "url",
"tags": [ "lego", ] ,
"images": [],
"description": ""
},{
"url": "http://danny316p.github.io/LEGO_and_Open_Source/s5/s5-lego_and_open_source.html",
"name": "LEGO and Open Source",
"dateAdd": "2018-07-24T07:11:48.804Z",
"dateUpdate": "2018-07-24T07:11:48.805Z",
"id": "a4d05536-f536-48f0-ac2c-5ead220eac71",
"type": "url",
"tags": [ "lego", ] ,
"images": [],
"description": ""
},{
"url": "https://github.com/danny316p/LEGO_and_Open_Source",
"name": "danny316p/LEGO_and_Open_Source: This is a slide-based presentation prepared for ease of use by anyone, anywhere, for use in discussing how the LEGO fan community and the open source community play off each other.",
"dateAdd": "2018-07-24T07:13:23.225Z",
"dateUpdate": "2018-07-24T07:13:23.226Z",
"id": "10156631-fbb3-493d-bdcc-3cb881b395b6",
"type": "url",
"tags": [ "lego", ] ,
"images": [],
"description": ""
},{
"url": "https://substack.neocities.org/brickworld.html",
"name": "bickworld ***",
"dateAdd": "2018-07-24T07:15:03.928Z",
"dateUpdate": "2019-03-02T10:07:25.030Z",
"id": "0d1c4de9-8e9c-4e9d-a8ad-3b19887b836e",
"type": "url",
"tags": [ "lego", ] ,
"images": [],
"description": ""
},{
"url": "http://uvs.propositions.org.uk/uvslongver.html",
"name": "Urban Versioning System 1.0",
"dateAdd": "2018-07-19T07:15:06.799Z",
"dateUpdate": "2018-07-24T04:45:21.459Z",
"id": "952a84bc-403b-412a-afb5-ea89742b5751",
"type": "url",
"tags": [ "manifestos", ] ,
"images": [],
"description": ""
},{
"url": "http://www.iwritewordsgood.com/apl/set.htm",
"name": "APL - Home",
"dateAdd": "2018-07-19T08:14:43.616Z",
"dateUpdate": "2019-02-10T08:15:26.553Z",
"id": "fe496ec1-7565-466b-8ff8-f792c9f0c4fa",
"type": "url",
"tags": [ "manifestos", ] ,
"images": [],
"description": ""
},{
"url": "http://www.internet-manifesto.org/",
"name": "Internet-Manifesto",
"dateAdd": "2017-12-31T19:33:50.000Z",
"dateUpdate": "2019-03-02T08:09:23.003Z",
"id": "2c7c1665-1b78-41a8-8d97-ad85e9893e29",
"type": "url",
"tags": [ "manifestos", ] ,
"images": [],
"description": ""
},{
"url": "http://archive.org/stream/GuerillaOpenAccessManifesto/Goamjuly2008_djvu.txt",
"name": "Full text of "Guerilla Open Access Manifesto"",
"dateAdd": "2017-12-31T19:33:50.000Z",
"dateUpdate": "2019-02-19T00:41:15.758Z",
"id": "7defd024-4802-4d17-a2cc-8943583727a9",
"type": "url",
"tags": [ "manifestos", ] ,
"images": [],
"description": ""
},{
"url": "http://www.andrewalexanderprice.com/index.php",
"name": "Andrew Alexander Price",
"dateAdd": "2018-07-21T09:42:27.107Z",
"dateUpdate": "2019-03-02T09:04:13.679Z",
"id": "3da4d686-75b1-4052-b244-2091bd1fd208",
"type": "url",
"tags": [ "news blogs sources", ] ,
"images": [],
"description": ""
},{
"url": "http://institutewithoutboundaries.ca/portfolio-category/projects/",
"name": "All Projects Archives - Institute Without Boundaries",
"dateAdd": "2018-07-21T20:10:19.429Z",
"dateUpdate": "2018-07-21T20:10:19.429Z",
"id": "9a920499-5379-4b48-b06f-b4d4fa338f50",
"type": "url",
"tags": [ "news blogs sources", ] ,
"images": [],
"description": ""
},{
"url": "https://jods.mitpress.mit.edu/",
"name": "Journal of Design and Science",
"dateAdd": "2018-07-24T03:54:34.850Z",
"dateUpdate": "2018-07-24T03:54:34.850Z",
"id": "d99f70ab-a101-4718-aa4b-ae27df2561a2",
"type": "url",
"tags": [ "news blogs sources", "mit" ] ,
"images": [],
"description": ""
},{
"url": "https://www.archdaily.com/",
"name": "ArchDaily | Broadcasting Architecture Worldwide",
"dateAdd": "2018-07-24T05:46:15.524Z",
"dateUpdate": "2019-03-02T09:06:08.752Z",
"id": "f536fc6d-2f27-419c-9f10-55934f6b0cde",
"type": "url",
"tags": [ "news blogs sources", ] ,
"images": [],
"description": ""
},{
"url": "https://blog.p2pfoundation.net/",
"name": "P2P Foundation | Researching, documenting and promoting peer to peer practices",
"dateAdd": "2018-07-25T07:19:47.860Z",
"dateUpdate": "2019-03-02T09:28:07.905Z",
"id": "1595efec-2114-4c34-81ae-39c7a9a4bd73",
"type": "url",
"tags": [ "news blogs sources", ] ,
"images": [],
"description": ""
},{
"url": "https://www.thingiverse.com/",
"name": "Thingiverse - Digital Designs for Physical Objects",
"dateAdd": "2018-07-24T05:50:40.935Z",
"dateUpdate": "2018-07-24T05:50:40.936Z",
"id": "52b1ad7f-1141-4316-bf59-fcc983324d3c",
"type": "url",
"tags": [ "open objects furniture", "thingiverse", ] ,
"images": [],
"description": ""
},{
"url": "https://en.wikipedia.org/wiki/Thingiverse",
"name": "Thingiverse - Wikipedia",
"dateAdd": "2018-07-24T05:50:26.300Z",
"dateUpdate": "2018-07-24T05:50:26.301Z",
"id": "410a3576-3485-4338-a984-a324ac74da2c",
"type": "url",
"tags": [ "open objects furniture", "thingiverse", "wikipedia" ] ,
"images": [],
"description": ""
},{
"url": "http://kwambio.com/#/",
"name": "3D Printing With Kwambio: Ceramics | Porcelain Objects",
"dateAdd": "2018-07-19T07:45:22.638Z",
"dateUpdate": "2018-07-24T04:41:21.212Z",
"id": "4a18fb4e-24fd-4242-9807-dcc645136fdd",
"type": "url",
"tags": [ "open objects furniture", "thingiverse", ] ,
"images": [],
"description": ""
},{
"url": "http://componance.com/",
"name": "Componance - Modern Architectural Hardware - USA and Canada",
"dateAdd": "2018-07-24T04:39:48.775Z",
"dateUpdate": "2018-07-24T04:39:48.775Z",
"id": "2a055fd1-f2a4-4135-a509-dc19e8d6d863",
"type": "url",
"tags": [ "open objects furniture", "thingiverse", ] ,
"images": [],
"description": ""
},{
"url": "http://componance.com/",
"name": "Componance - Modern Architectural Hardware - USA and Canada",
"dateAdd": "2018-07-19T07:50:06.947Z",
"dateUpdate": "2018-07-24T04:39:48.775Z",
"id": "90fff27a-12f2-4c4e-9ec1-76c02b4251ac",
"type": "url",
"tags": [ "open objects furniture", "thingiverse", ] ,
"images": [],
"description": ""
},{
"url": "https://www.fabhub.io/",
"name": "FabHub - Digital Fabrication Hub",
"dateAdd": "2018-07-19T07:48:45.344Z",
"dateUpdate": "2018-07-24T04:38:51.249Z",
"id": "e8e33a81-5510-4842-9aa5-df8eea908f67",
"type": "url",
"tags": [ "open objects furniture", "thingiverse", ] ,
"images": [],
"description": ""
},{
"url": "http://beta.openstructures.net/",
"name": "Home.",
"dateAdd": "2018-07-19T07:38:24.160Z",
"dateUpdate": "2019-03-03T01:30:26.016Z",
"id": "6bb6eb2a-11a9-4db1-9b09-ffc140e5aa10",
"type": "url",
"tags": [ "open objects furniture", "thingiverse", ] ,
"images": [],
"description": ""
},{
"url": "https://offspring.lifehacker.com/heres-how-your-kids-can-build-lego-models-digitally-and-1827634553",
"name": "How to Create Your Own Lego Models and Buy Them",
"dateAdd": "2018-07-17T01:37:56.549Z",
"dateUpdate": "2018-07-17T01:37:56.550Z",
"id": "8a213eff-cd67-4e44-bd8a-633b9f33c974",
"type": "url",
"tags": [ "open objects furniture", "thingiverse", ] ,
"images": [],
"description": ""
},{
"url": "https://www.opensourceecology.org/gvcs/",
"name": "Machines: Global Village Construction Set | Open Source Ecology",
"dateAdd": "2018-07-01T09:59:46.823Z",
"dateUpdate": "2018-07-25T07:10:00.343Z",
"id": "a936f360-cad8-4cc0-bd29-7d2039fa347f",
"type": "url",
"tags": [ "open objects furniture", "thingiverse", ] ,
"images": [],
"description": ""
},{
"url": "https://n-e-r-v-o-u-s.com/labs/",
"name": "Nervous System | labs",
"dateAdd": "2018-07-19T07:30:31.995Z",
"dateUpdate": "2019-03-16T19:31:27.272Z",
"id": "7790bdf0-4d80-4eca-bb3a-e931128d4844",
"type": "url",
"tags": [ "open objects furniture", "thingiverse", ] ,
"images": [],
"description": ""
},{
"url": "http://www.openplan.com/",
"name": "Open Plan Systems - Office Furniture in Richmond, VA",
"dateAdd": "2018-07-19T07:47:32.109Z",
"dateUpdate": "2018-07-24T04:40:15.460Z",
"id": "b91cb814-7fa9-4a60-93a0-c1b4f5dea488",
"type": "url",
"tags": [ "open objects furniture", "thingiverse", ] ,
"images": [],
"description": ""
},{
"url": "http://www.openstructures.net/",
"name": "OS - OpenStructures",
"dateAdd": "2018-07-07T07:08:48.466Z",
"dateUpdate": "2019-03-03T01:29:18.575Z",
"id": "3308f75e-ebd9-46a0-80f6-f054a87d64e9",
"type": "url",
"tags": [ "open objects furniture", "thingiverse", ] ,
"images": [],
"description": ""
},{
"url": "http://www.partandwhole.com/",
"name": "Part & Whole – Contemporary Canadian Design",
"dateAdd": "2018-07-19T07:46:48.512Z",
"dateUpdate": "2018-07-24T04:40:51.356Z",
"id": "b4b82fa3-e5a2-4578-81dd-c30d758c78db",
"type": "url",
"tags": [ "open objects furniture", "thingiverse", ] ,
"images": [],
"description": ""
},{
"url": "https://grabcad.com/library",
"name": "Popular models | 3D CAD Model Collection | GrabCAD Community Library",
"dateAdd": "2018-07-19T08:26:14.919Z",
"dateUpdate": "2018-07-19T08:26:14.919Z",
"id": "57f4ed0a-aac9-41bb-982d-b0e15e6aa01a",
"type": "url",
"tags": [ "open objects furniture", "thingiverse", ] ,
"images": [],
"description": ""
},{
"url": "https://www.sculpteo.com/en/",
"name": "Sculpteo | Online 3D Printing Service for your 3D design",
"dateAdd": "2018-07-19T07:44:31.732Z",
"dateUpdate": "2018-07-24T04:41:22.031Z",
"id": "82d574f9-ce0f-474c-af05-b66aa2fc64f0",
"type": "url",
"tags": [ "open objects furniture", "thingiverse", ] ,
"images": [],
"description": ""
},{
"url": "https://www.shapeways.com/",
"name": "Shapeways - 3D Printing Service and Marketplace",
"dateAdd": "2018-07-19T07:44:11.569Z",
"dateUpdate": "2018-07-19T07:44:11.570Z",
"id": "d82508da-797b-436e-acf9-c4650daa0031",
"type": "url",
"tags": [ "open objects furniture", "thingiverse", ] ,
"images": [],
"description": ""
},{
"url": "https://tylko.com/",
"name": "Tylko: The Perfect Shelf for Your Home",
"dateAdd": "2018-07-19T07:46:08.861Z",
"dateUpdate": "2018-07-24T04:40:54.133Z",
"id": "79277fa1-0932-4253-b893-fa94d68d44d5",
"type": "url",
"tags": [ "open objects furniture", "thingiverse", ] ,
"images": [],
"description": ""
},{
"url": "https://www.you3dit.com/",
"name": "You3Dit - 3D Design and Fabrication Platform - Make Anything, Anywhere! Bring your custom ideas to life!",
"dateAdd": "2018-07-19T08:27:35.361Z",
"dateUpdate": "2019-03-02T09:55:10.249Z",
"id": "652edfdf-a726-49e8-a9e4-3de15242e217",
"type": "url",
"tags": [ "open objects furniture", "thingiverse", ] ,
"images": [],
"description": ""
},{
"url": "https://formlabs.com/",
"name": "High Resolution SLA and SLS 3D Printers for Professionals | Formlabs",
"dateAdd": "2018-07-24T05:53:13.758Z",
"dateUpdate": "2018-07-24T05:53:13.759Z",
"id": "7a98280e-9581-4cf8-ac09-4af8ed1e222a",
"type": "url",
"tags": [ "open objects furniture", "thingiverse", ] ,
"images": [],
"description": ""
},{
"url": "https://github.com/afomi",
"name": "afomi (Ryan Wold)",
"dateAdd": "2018-05-03T07:44:38.000Z",
"dateUpdate": "2019-02-21T10:16:11.565Z",
"id": "64c9180d-f0c7-40b5-b447-9f99c4e1ff12",
"type": "url",
"tags": [ "opentecture", ] ,
"images": [],
"description": ""
},{
"url": "https://www.opentecture.com/",
"name": "Opentecture",
"dateAdd": "2018-07-21T19:27:21.636Z",
"dateUpdate": "2019-02-12T03:49:23.574Z",
"id": "d59e91d9-c64b-4361-8640-daa4fae6a6c8",
"type": "url",
"tags": [ "opentecture", ] ,
"images": [],
"description": ""
},{
"url": "https://github.com/opentecture",
"name": "Opentecture github",
"dateAdd": "2018-05-04T07:51:00.000Z",
"dateUpdate": "2019-04-07T00:42:53.242Z",
"id": "ff9f1238-dd94-4b30-acd2-72e88832624c",
"type": "url",
"tags": [ "opentecture", ] ,
"images": [],
"description": ""
},{
"url": "https://github.com/opentecture/open-resources",
"name": "opentecture/open-resources: Shared, open resources (references, links, inspiration, and more)",
"dateAdd": "2018-05-04T07:54:04.000Z",
"dateUpdate": "2019-02-10T23:47:51.885Z",
"id": "76f99ac9-3d9d-4e13-83a0-3c8864b5b738",
"type": "url",
"tags": [ "opentecture", ] ,
"images": [],
"description": ""
},{
"url": "https://network.aia.org/buildingperformancecommunity/home",
"name": "Home - Building Performance Community",
"dateAdd": "2018-07-22T01:14:26.258Z",
"dateUpdate": "2018-07-24T03:51:27.774Z",
"id": "8d648e3d-7dc0-455f-9ee5-6e74f32bb923",
"type": "url",
"tags": [ "organizations", "american-institute-architects", ] ,
"images": [],
"description": ""
},{
"url": "https://www.openbuildinginstitute.org/",
"name": "Open Building Institute",
"dateAdd": "2018-07-19T07:43:32.896Z",
"dateUpdate": "2018-07-25T07:17:10.548Z",
"id": "0d540e10-9e79-4b06-a0bb-0e9fe1c7f977",
"type": "url",
"tags": [ "organizations", "open-building-institute", ] ,
"images": [],
"description": ""
},{
"url": "https://www.opensourceecology.org/",
"name": "Open Source Ecology",
"dateAdd": "2018-07-25T07:19:23.183Z",
"dateUpdate": "2018-07-25T07:19:23.183Z",
"id": "31a5b88b-09d8-4263-a058-573edcab3bf5",
"type": "url",
"tags": [ "organizations", "open-source-ecology", ] ,
"images": [],
"description": ""
},{
"url": "https://www.z33.be/contact/",
"name": "About — z33",
"dateAdd": "2018-07-20T08:06:25.519Z",
"dateUpdate": "2019-03-02T09:54:35.818Z",
"id": "7a4a8b67-8f05-4416-8d3a-0a4695b286da",
"type": "url",
"tags": [ "organizations", "open-source-ecology", ] ,
"images": [],
"description": ""
},{
"url": "https://opensource.com/about",
"name": "About Opensource.com | Opensource.com",
"dateAdd": "2018-07-20T08:31:16.997Z",
"dateUpdate": "2018-07-21T09:52:30.285Z",
"id": "fe30d7bd-7972-4c12-afbc-e2f3d1a33156",
"type": "url",
"tags": [ "organizations", "open-source-ecology", ] ,
"images": [],
"description": ""
},{
"url": "http://www.sensorica.co/home/about-us",
"name": "About us - SENSORICA",
"dateAdd": "2018-07-20T08:40:43.857Z",
"dateUpdate": "2019-03-02T09:48:54.062Z",
"id": "19375a61-23d1-48b4-a2bf-6214d6d480d8",
"type": "url",
"tags": [ "organizations", "open-source-ecology", ] ,
"images": [],
"description": ""
},{
"url": "http://acadia.org/feed",
"name": "ACADIA",
"dateAdd": "2018-08-12T08:23:37.783Z",
"dateUpdate": "2019-04-14T07:11:00.018Z",
"id": "af1a41fb-6656-4998-bef5-5ba7b0ed0c01",
"type": "url",
"tags": [ "organizations", "open-source-ecology", ] ,
"images": [],
"description": ""
},{
"url": "http://www.openbricks.io/",
"name": "Bricks, the hub for collaborative design & open source architecture",
"dateAdd": "2018-07-19T09:04:35.155Z",
"dateUpdate": "2019-02-10T01:02:18.555Z",
"id": "b945dcfc-27f8-456c-92db-928054221d50",
"type": "url",
"tags": [ "organizations", "open-source-ecology", ] ,
"images": [],
"description": ""
},{
"url": "https://www.opendesign.com/",
"name": "Home | Open Design Alliance",
"dateAdd": "2018-07-20T08:04:05.293Z",
"dateUpdate": "2018-07-21T09:53:22.347Z",
"id": "a6f1c645-caba-40e7-b546-08c3a146349a",
"type": "url",
"tags": [ "organizations", "open-source-ecology", ] ,
"images": [],
"description": ""
},{
"url": "https://p2pfoundation.net/",
"name": "Home Page - P2P Foundation",
"dateAdd": "2018-07-25T07:20:26.833Z",
"dateUpdate": "2018-07-25T07:23:58.703Z",
"id": "103ef270-93a3-47aa-b67c-6a979acd7124",
"type": "url",
"tags": [ "organizations", "open-source-ecology", ] ,
"images": [],
"description": ""
},{
"url": "http://openarchcollab.org/",
"name": "Open Architecture Collaborative – Social Design for Social Justice",
"dateAdd": "2018-07-20T08:34:03.545Z",
"dateUpdate": "2018-07-25T07:25:53.432Z",
"id": "dd3de468-c193-4e7d-8f62-cce19ed4c3b0",
"type": "url",
"tags": [ "organizations", "open-source-ecology", ] ,
"images": [],
"description": ""
},{
"url": "http://www.open-building.org/ob/concepts.html",
"name": "Open Building Concepts",
"dateAdd": "2018-07-19T08:05:45.954Z",
"dateUpdate": "2018-07-25T07:20:57.584Z",
"id": "afd01c7f-2162-41bc-ba88-228d61dac94d",
"type": "url",
"tags": [ "organizations", "open-source-ecology", ] ,
"images": [],
"description": ""
},{
"url": "https://web.archive.org/web/20120302133414/http://www2.parc.com/csl/groups/sda/projects/oi/site-guide.html",
"name": "Open Implementation Site Guide",
"dateAdd": "2018-07-20T08:26:56.032Z",
"dateUpdate": "2018-07-25T07:15:53.674Z",
"id": "486a9eda-dc8a-4b95-8513-66cca274da9d",
"type": "url",
"tags": [ "organizations", "open-source-ecology", ] ,
"images": [],
"description": ""
},{
"url": "https://www.metsawood.com/global/Campaigns/planb/open-source-wood/Pages/default.aspx",
"name": "Open Source Wood",
"dateAdd": "2018-07-19T08:00:54.923Z",
"dateUpdate": "2019-03-02T10:18:30.909Z",
"id": "44f44ac5-33f0-4a0b-9d4b-b598b9bb00c3",
"type": "url",
"tags": [ "organizations", "open-source-ecology", ] ,
"images": [],
"description": ""
},{
"url": "https://blog.p2pfoundation.net/",
"name": "P2P Foundation | Researching, documenting and promoting peer to peer practices",
"dateAdd": "2018-07-19T09:07:10.341Z",
"dateUpdate": "2019-03-02T09:28:07.905Z",
"id": "45ee1a21-5969-4407-9eca-50e25ccb4de4",
"type": "url",
"tags": [ "organizations", "open-source-ecology", ] ,
"images": [],
"description": ""
},{
"url": "http://www.rsd7.org/",
"name": "RSD7 - RELATING SYSTEMS THINKING AND DESIGN 7 SYMPOSIUM",
"dateAdd": "2018-07-24T04:47:41.940Z",
"dateUpdate": "2019-03-02T10:14:36.084Z",
"id": "65d909da-217b-4ad3-bd34-342d3cb66e3a",
"type": "url",
"tags": [ "organizations", "open-source-ecology", ] ,
"images": [],
"description": ""
},{
"url": "https://www.smartgeometry.org/sg2016-gothenburg/",
"name": "sg2016 Gothenburg — smartgeometry",
"dateAdd": "2018-07-19T07:22:43.359Z",
"dateUpdate": "2018-07-21T09:51:58.638Z",
"id": "77286098-2497-408e-b306-2fd887d11413",
"type": "url",
"tags": [ "organizations", "open-source-ecology", ] ,
"images": [],
"description": ""
},{
"url": "https://www.smartgeometry.org/",
"name": "smartgeometry",
"dateAdd": "2018-07-24T04:48:41.802Z",
"dateUpdate": "2018-07-24T04:48:41.802Z",
"id": "6d9e30e4-0554-4255-b832-b67482964261",
"type": "url",
"tags": [ "organizations", "open-source-ecology", ] ,
"images": [],
"description": ""
},{
"url": "https://systemic-design.net/sdrn/",
"name": "Systemic Design Research Network « Systemic Design",
"dateAdd": "2018-07-19T07:16:54.007Z",
"dateUpdate": "2018-07-19T07:16:54.008Z",
"id": "1acb9f3a-7813-4870-8e08-d34692e40c02",
"type": "url",
"tags": [ "organizations", "open-source-ecology", ] ,
"images": [],
"description": ""
},{
"url": "https://web.archive.org/web/20160731220354/http://openarchitecturenetwork.org/",
"name": "Wayback Machine",
"dateAdd": "2018-07-20T08:42:25.662Z",
"dateUpdate": "2018-07-20T08:42:25.663Z",
"id": "34003435-ea8d-46f9-8e7c-6fe4f56eaafb",
"type": "url",
"tags": [ "organizations", "open-source-ecology", ] ,
"images": [],
"description": ""
},{
"url": "http://www.web3d.org/",
"name": "Web3D Consortium - Royalty Free, Open Standards for Real-Time 3D Communication",
"dateAdd": "2017-12-31T07:13:31.000Z",
"dateUpdate": "",
"id": "9f7c36cc-24d0-42e5-80f2-d5d798db01e0",
"type": "url",
"tags": [ "organizations", "open-source-ecology", ] ,
"images": [],
"description": ""
},{
"url": "https://twitter.com/AlastairParvin?ref_src=twsrc%5Egoogle%7Ctwcamp%5Eserp%7Ctwgr%5Eauthor",
"name": "Alastair Parvin (@AlastairParvin) | Twitter",
"dateAdd": "2018-07-24T05:37:46.728Z",
"dateUpdate": "2018-07-24T05:48:11.394Z",
"id": "5f2107ce-ff31-44ac-808d-fde5ab01ddf0",
"type": "url",
"tags": [ "people", "alastair-parvin", ] ,
"images": [],
"description": ""
},{
"url": "https://www.opensystemslab.io/hello-world",
"name": "opensystemslab",
"dateAdd": "2018-07-24T05:37:21.563Z",
"dateUpdate": "2018-07-24T05:41:09.301Z",
"id": "255f1648-f0a7-4733-9d7e-9cef1081b495",
"type": "url",
"tags": [ "people", "alastair-parvin", ] ,
"images": [],
"description": ""
},{
"url": "https://medium.com/@AlastairParvin",
"name": "Alastair Parvin – Medium",
"dateAdd": "2018-07-24T05:41:37.714Z",
"dateUpdate": "2018-07-24T05:41:37.714Z",
"id": "283f314a-ba0b-4c5c-97f1-0d1c2ed1525d",
"type": "url",
"tags": [ "people", "alastair-parvin", ] ,
"images": [],
"description": ""
},{
"url": "https://www.wired.com/2008/09/sl-joachim/",
"name": "Mitchell Joachim: Redesign Cities From Scratch | WIRED",
"dateAdd": "2018-07-19T07:31:52.335Z",
"dateUpdate": "2018-07-24T04:08:16.230Z",
"id": "3ffdf017-603f-4bce-9a2e-74fb8960f296",
"type": "url",
"tags": [ "people", "mitchell-joachim", ] ,
"images": [],
"description": ""
},{
"url": "http://www.archinode.com/bio.html",
"name": "Mitchell Joachim, Terreform",
"dateAdd": "2018-07-19T07:31:36.612Z",
"dateUpdate": "2019-03-02T09:10:03.409Z",
"id": "5d3f1b79-52bd-4867-aaea-eb9c0f9b8e36",
"type": "url",
"tags": [ "people", "mitchell-joachim", ] ,
"images": [],
"description": ""
},{
"url": "http://we.openbricks.io/post/121439352247/team",
"name": "Building Bricks — Bricks team",
"dateAdd": "2018-07-24T06:24:41.923Z",
"dateUpdate": "2018-07-24T06:24:41.923Z",
"id": "6937bb2a-bf61-4263-a36f-053fbd58f978",
"type": "url",
"tags": [ "people", "sebastien-lucas", ] ,
"images": [],
"description": ""
},{
"url": "https://github.com/sinsunsan",
"name": "sinsunsan (Sébastien LUCAS)",
"dateAdd": "2018-07-24T06:25:58.618Z",
"dateUpdate": "2018-07-24T06:25:58.619Z",
"id": "c9dd37dd-db8b-41fc-81dc-0e4b427d04a0",
"type": "url",
"tags": [ "people", "sebastien-lucas", ] ,
"images": [],
"description": ""
},{
"url": "https://www.linkedin.com/in/thomas-lomm%C3%A9e-088b535/",
"name": "(7) Thomas Lommée | LinkedIn",
"dateAdd": "2018-07-24T05:59:47.013Z",
"dateUpdate": "2018-07-24T05:59:47.013Z",
"id": "51d8d37e-85bd-4b09-9de2-6539dcbbd235",
"type": "url",
"tags": [ "people", "thomas-lomee", ] ,
"images": [],
"description": ""
},{
"url": "http://dasdynamischearchiv.de/thomas-lommee/",
"name": "Thomas Lommée - Das Dynamische Archiv",
"dateAdd": "2018-07-24T06:01:20.100Z",
"dateUpdate": "2018-07-24T06:01:20.100Z",
"id": "15eaad95-5b2d-4134-8217-6ba1c608b285",
"type": "url",
"tags": [ "people", "thomas-lomee", ] ,
"images": [],
"description": ""
},{
"url": "https://www.capa-city-ensuf.eu/projectteam/",
"name": "Project team – CAPA CITY",
"dateAdd": "2018-07-24T06:02:43.320Z",
"dateUpdate": "2018-07-24T06:02:43.321Z",
"id": "a25e24f0-74e1-4de0-801b-23226c2fb000",
"type": "url",
"tags": [ "people", "thomas-lomee", ] ,
"images": [],
"description": ""
},{
"url": "https://www.artstation.com/jakubowski",
"name": "ArtStation - Marcin Jakubowski",
"dateAdd": "2018-07-25T07:27:09.932Z",
"dateUpdate": "2019-03-02T09:14:35.404Z",
"id": "f862c8d8-fb08-4bc9-92a8-a347f885ead4",
"type": "url",
"tags": [ "people", "thomas-lomee", ] ,
"images": [],
"description": ""
},{
"url": "http://www.habraken.com/",
"name": "Home Page John Habraken",
"dateAdd": "2018-07-19T08:08:12.820Z",
"dateUpdate": "2018-07-24T04:07:27.988Z",
"id": "7873b4ae-df1b-4b8e-aadc-419bd2bd730d",
"type": "url",
"tags": [ "people", "thomas-lomee", ] ,
"images": [],
"description": ""
},{
"url": "https://3dwarehouse.sketchup.com/user/1003226431471152943718096/Marcin-J?nav=models",
"name": "Marcin J. - 3D Warehouse",
"dateAdd": "2018-07-25T07:27:34.327Z",
"dateUpdate": "2019-04-14T06:30:00.538Z",
"id": "6267e36a-e800-4e34-ab5a-1b61705a3637",
"type": "url",
"tags": [ "people", "thomas-lomee", ] ,
"images": [],
"description": ""
},{
"url": "http://alhadidi.com/redefining-innovation-in-the-architectural-practice/",
"name": "REDEFINING INNOVATION IN THE ARCHITECTURAL PRACTICE – Suleiman Alhadidi",
"dateAdd": "2018-06-20T09:53:44.921Z",
"dateUpdate": "2019-03-02T09:00:45.891Z",
"id": "32496adc-6502-4256-b0f4-730b8fb8c175",
"type": "url",
"tags": [ "people", "thomas-lomee", ] ,
"images": [],
"description": ""
},{
"url": "https://ablersite.org/projects/",
"name": "Sara Hendren. projects. | Abler.",
"dateAdd": "2018-07-19T07:34:37.078Z",
"dateUpdate": "2019-04-14T07:06:52.117Z",
"id": "11861d02-59b3-4a3f-b03f-3c3fff04ca8e",
"type": "url",
"tags": [ "people", "thomas-lomee", ] ,
"images": [],
"description": ""
},{
"url": "http://www.openobject.org/",
"name": "Scott Mitchell open object",
"dateAdd": "2018-07-19T07:26:32.376Z",
"dateUpdate": "2018-07-24T04:56:49.987Z",
"id": "ad3c0a3b-3934-4254-938a-d52bb2a0530e",
"type": "url",
"tags": [ "people", "thomas-lomee", ] ,
"images": [],
"description": ""
},{
"url": "http://www.designeducation.ca/",
"name": "DesignEducation.ca - Thousands of Design Resources",
"dateAdd": "2017-12-31T19:33:49.000Z",
"dateUpdate": "2019-03-02T08:07:17.490Z",
"id": "437daead-fbbc-42b2-b005-9498ff2eb830",
"type": "url",
"tags": [ "portals", ] ,
"images": [],
"description": ""
},{
"url": "http://www.wikiwand.com/en/Modular_building#",
"name": "Modular building - Wikiwand",
"dateAdd": "2018-07-21T20:28:00.946Z",
"dateUpdate": "2019-03-02T09:57:46.170Z",
"id": "f7e7ca40-4a2b-4883-8f5e-b2f69bdcfced",
"type": "url",
"tags": [ "portals", ] ,
"images": [],
"description": ""
},{
"url": "http://www.openbricks.io/",
"name": "Bricks, the hub for collaborative design & open source architecture",
"dateAdd": "2018-07-24T06:22:16.130Z",
"dateUpdate": "2019-02-10T01:02:18.555Z",
"id": "560ac81a-2adb-4b6d-8ca7-03c5dc614ec3",
"type": "url",
"tags": [ "portals", ] ,
"images": [],
"description": ""
},{
"url": "https://github.com/obricks/open-source-architecture",
"name": "obricks/open-source-architecture: A directory of open source architecture ressources: platforms, communities, projects...",
"dateAdd": "2018-07-24T06:25:22.121Z",
"dateUpdate": "2018-07-24T06:25:22.121Z",
"id": "454eec86-459e-403b-93d2-e54f1a650294",
"type": "url",
"tags": [ "portals", ] ,
"images": [],
"description": ""
},{
"url": "https://www.blokable.com/",
"name": "Blokable",
"dateAdd": "2018-07-19T08:05:04.158Z",
"dateUpdate": "2019-03-02T09:29:05.705Z",
"id": "2c2276af-73ef-4b49-9e55-15a52dd010b0",
"type": "url",
"tags": [ "products kits", ] ,
"images": [],
"description": ""
},{
"url": "https://www.bluhomes.com/",
"name": "Blu Homes | Modern, Green, Premium Prefab Modular Bay Area Homes",
"dateAdd": "2018-07-19T08:04:51.403Z",
"dateUpdate": "2018-07-24T04:20:59.527Z",
"id": "41a7db2d-1c63-4ace-a53c-50885137116e",
"type": "url",
"tags": [ "products kits", ] ,
"images": [],
"description": ""
},{
"url": "https://bonestructure.ca/en/",
"name": "BONE Structure | Steel Construction System for Net Zero Energy Ready Homes",
"dateAdd": "2018-07-19T08:04:26.941Z",
"dateUpdate": "2019-04-14T08:10:25.216Z",
"id": "fdcd7d87-e74b-46bd-b17b-b0e0005b1ac0",
"type": "url",
"tags": [ "products kits", ] ,
"images": [],
"description": ""
},{
"url": "http://www.avavadwellings.com/",
"name": "Home | Avava Dwellings",
"dateAdd": "2018-07-19T07:36:18.305Z",
"dateUpdate": "2019-03-02T09:20:24.353Z",
"id": "75aa9be0-3a1e-439f-bf55-1399de359a3f",
"type": "url",
"tags": [ "products kits", ] ,
"images": [],
"description": ""
},{
"url": "http://www.metal-building-homes.com/",
"name": "Metal Building Homes Guide",
"dateAdd": "2018-07-19T07:42:10.776Z",
"dateUpdate": "2018-07-19T07:42:31.148Z",
"id": "0fdeb989-a182-4660-bbdf-365925d6d215",
"type": "url",
"tags": [ "products kits", ] ,
"images": [],
"description": ""
},{
"url": "https://factoryos.com/",
"name": "Modular Buildings For Modern Families | Factory OS",
"dateAdd": "2018-07-19T08:02:04.662Z",
"dateUpdate": "2018-07-24T04:21:57.135Z",
"id": "161ddd80-fdc4-4042-9bd0-9b3cdd514c1c",
"type": "url",
"tags": [ "products kits", ] ,
"images": [],
"description": ""
},{
"url": "http://projectfrog.com/about/team",
"name": "Team | Project Frog",
"dateAdd": "2018-07-19T07:20:52.823Z",
"dateUpdate": "2018-07-19T07:20:52.824Z",
"id": "a0520e88-fade-4c5a-bde7-61732bc5e45c",
"type": "url",
"tags": [ "products kits", ] ,
"images": [],
"description": ""
},{
"url": "http://www.hermithouses.nl/",
"name": "The Hermit Houses",
"dateAdd": "2017-12-31T19:33:50.000Z",
"dateUpdate": "2018-07-21T09:37:19.516Z",
"id": "f78f8965-e0d5-46b7-a3ca-8e07325fd2fe",
"type": "url",
"tags": [ "products kits", "mit" ] ,
"images": [],
"description": ""
},{
"url": "https://www.bluhomes.com/design_studio/",
"name": "Unity WebGL Player | Blu Design Studio",
"dateAdd": "2018-07-19T07:58:08.396Z",
"dateUpdate": "2018-07-24T04:27:24.504Z",
"id": "300f8483-b8d8-4e93-a2e3-55e52011a8c3",
"type": "url",
"tags": [ "products kits", ] ,
"images": [],
"description": ""
},{
"url": "https://unityhomes.com/",
"name": "Welcome - Unity Homes",
"dateAdd": "2018-07-19T07:58:40.993Z",
"dateUpdate": "2018-07-24T04:25:46.698Z",
"id": "c1858af1-2c4b-4ed3-bdeb-174ae9ecb182",
"type": "url",
"tags": [ "products kits", ] ,
"images": [],
"description": ""
},{
"url": "https://www.wikkelhouse.com/",
"name": "Wikkelhouse - A HOUSE FOR YOU",
"dateAdd": "2018-07-19T07:58:52.946Z",
"dateUpdate": "2019-03-02T09:56:58.259Z",
"id": "522c78a8-40c7-41b8-b08a-1d107328bc28",
"type": "url",
"tags": [ "products kits", ] ,
"images": [],
"description": ""
},{
"url": "https://intellistructures.com/",
"name": "IntelliStructures, Inc",
"dateAdd": "2018-07-24T04:23:18.410Z",
"dateUpdate": "2019-03-02T10:19:38.908Z",
"id": "c10f28fe-895e-4d71-acb2-9fdfd88c4af1",
"type": "url",
"tags": [ "products kits", ] ,
"images": [],
"description": ""
},{
"url": "chrome://bookmarks/?id=324476",
"name": "Bookmarks",
"dateAdd": "2018-07-24T04:16:32.386Z",
"dateUpdate": "2019-02-09T23:24:58.981Z",
"id": "0e61adff-1450-4ebf-b92b-8ed60aeb7568",
"type": "url",
"tags": [ "reference", "papers", ] ,
"images": [],
"description": ""
},{
"url": "https://en.wikipedia.org/wiki/3D_printing_marketplace",
"name": "3D printing marketplace - Wikipedia",
"dateAdd": "2018-07-24T05:54:10.338Z",
"dateUpdate": "2018-07-24T05:54:10.338Z",
"id": "e2a0c237-43eb-4bbb-8269-0e5bf655e496",
"type": "url",
"tags": [ "reference", "papers", "wikipedia" ] ,
"images": [],
"description": ""
},{
"url": "https://en.wikipedia.org/wiki/3DLT",
"name": "3DLT - Wikipedia",
"dateAdd": "2018-07-24T05:55:06.030Z",
"dateUpdate": "2018-07-24T05:55:06.030Z",
"id": "b116f8be-c104-4120-861c-b79b4cdb341f",
"type": "url",
"tags": [ "reference", "papers", "wikipedia" ] ,
"images": [],
"description": ""
},{
"url": "https://en.wikipedia.org/wiki/Architecture_for_Humanity",
"name": "Architecture for Humanity - Wikipedia",
"dateAdd": "2018-07-20T08:33:25.143Z",
"dateUpdate": "2018-07-24T06:18:15.312Z",
"id": "5ae09fd4-1901-48d9-8982-195de71e450f",
"type": "url",
"tags": [ "reference", "papers", "wikipedia" ] ,
"images": [],
"description": ""
},{
"url": "https://en.wikipedia.org/wiki/Co-creation",
"name": "Co-creation - Wikipedia",
"dateAdd": "2018-07-20T08:16:40.531Z",
"dateUpdate": "2018-07-20T08:16:40.532Z",
"id": "5a0caf89-b3b4-41e1-aa7f-66c811e439eb",
"type": "url",
"tags": [ "reference", "papers", "wikipedia" ] ,
"images": [],
"description": ""
},{
"url": "https://en.wikipedia.org/wiki/List_of_open-source_hardware_projects",
"name": "List of open-source hardware projects - Wikipedia",
"dateAdd": "2018-07-24T05:56:27.818Z",
"dateUpdate": "2018-07-24T05:56:27.818Z",
"id": "312ba9d7-0dd2-42c0-8758-35adcf38f0ba",
"type": "url",
"tags": [ "reference", "papers", "wikipedia" ] ,
"images": [],
"description": ""
},{
"url": "https://en.wikipedia.org/wiki/Materialise_NV",
"name": "Materialise NV - Wikipedia",
"dateAdd": "2018-07-24T05:54:35.205Z",
"dateUpdate": "2018-07-24T05:54:35.205Z",
"id": "52fb8ac6-02ce-41e7-8b60-a04df538c750",
"type": "url",
"tags": [ "reference", "papers", "wikipedia" ] ,
"images": [],
"description": ""
},{
"url": "https://en.wikipedia.org/wiki/Open_Architecture_Network",
"name": "Open Architecture Network - Wikipedia",
"dateAdd": "2018-07-19T08:53:29.889Z",
"dateUpdate": "2018-07-20T08:32:44.764Z",
"id": "df89d834-dfd1-4d7a-8d9a-43d4ed2aad6b",
"type": "url",
"tags": [ "reference", "papers", "wikipedia" ] ,
"images": [],
"description": ""
},{
"url": "https://en.wikipedia.org/wiki/Open_design",
"name": "Open design - Wikipedia",
"dateAdd": "2018-07-19T08:49:02.603Z",
"dateUpdate": "2018-07-20T08:43:28.532Z",
"id": "ab253671-f14e-42b6-97f1-65cc14bb3e23",
"type": "url",
"tags": [ "reference", "papers", "wikipedia" ] ,
"images": [],
"description": ""
},{
"url": "https://en.wikipedia.org/wiki/Open_Design_Alliance",
"name": "Open Design Alliance - Wikipedia",
"dateAdd": "2018-07-19T08:50:35.165Z",
"dateUpdate": "2018-07-20T08:02:25.755Z",
"id": "9f0bd798-9e11-4b1b-9b52-c00d108f7d1f",
"type": "url",
"tags": [ "reference", "papers", "wikipedia" ] ,
"images": [],
"description": ""
},{
"url": "https://en.wikipedia.org/wiki/Open_innovation",
"name": "Open innovation - Wikipedia",
"dateAdd": "2018-07-20T08:38:54.692Z",
"dateUpdate": "2018-07-20T08:38:54.692Z",
"id": "6128a7f2-615d-47ce-b842-55df21164a1e",
"type": "url",
"tags": [ "reference", "papers", "wikipedia" ] ,
"images": [],
"description": ""
},{
"url": "https://en.wikipedia.org/wiki/Open_standard",
"name": "Open standard - Wikipedia",
"dateAdd": "2018-07-20T08:27:31.439Z",
"dateUpdate": "2018-07-20T08:27:31.439Z",
"id": "968234b0-f71e-4683-b903-18cfe0cf22df",
"type": "url",
"tags": [ "reference", "papers", "wikipedia" ] ,
"images": [],
"description": ""
},{
"url": "https://en.wikipedia.org/wiki/Open-source_architecture",
"name": "Open-source architecture - Wikipedia",
"dateAdd": "2018-07-07T04:43:42.630Z",
"dateUpdate": "2019-02-18T03:00:19.934Z",
"id": "8a43eedc-d609-43b2-9590-8f084ccd7dc6",
"type": "url",
"tags": [ "reference", "papers", "wikipedia" ] ,
"images": [],
"description": ""
},{
"url": "https://en.wikipedia.org/wiki/Open-source_architecture",
"name": "Open-source architecture - Wikipedia",
"dateAdd": "2018-07-20T08:08:09.452Z",
"dateUpdate": "2019-02-18T03:00:19.934Z",
"id": "cd3322e7-8a0c-4e54-8ae4-698a8ccb780a",
"type": "url",
"tags": [ "reference", "papers", "wikipedia" ] ,
"images": [],
"description": ""
},{
"url": "https://en.wikipedia.org/wiki/Open-source_model",
"name": "Open-source model - Wikipedia",
"dateAdd": "2018-07-20T08:00:49.260Z",
"dateUpdate": "2018-07-20T08:00:49.261Z",
"id": "a7f1f978-9c0f-43b0-a4fb-778ba0dc4486",
"type": "url",
"tags": [ "reference", "papers", "wikipedia" ] ,
"images": [],
"description": ""
},{
"url": "https://en.wikipedia.org/wiki/OpenStructures",
"name": "OpenStructures - Wikipedia",
"dateAdd": "2018-07-19T08:39:29.519Z",
"dateUpdate": "2019-01-20T22:51:39.449Z",
"id": "05ff89af-2f65-4802-b1b0-8dc14d502500",
"type": "url",
"tags": [ "reference", "papers", "wikipedia" ] ,
"images": [],
"description": ""
},{
"url": "https://en.wikipedia.org/wiki/Sculpteo",
"name": "Sculpteo - Wikipedia",
"dateAdd": "2018-07-24T05:55:27.359Z",
"dateUpdate": "2018-07-24T05:55:27.359Z",
"id": "a83fa872-0705-43b4-bf72-c26ce95bbb9b",
"type": "url",
"tags": [ "reference", "papers", "wikipedia" ] ,
"images": [],
"description": ""
},{
"url": "https://en.wikipedia.org/wiki/Sears_Catalog_Home",
"name": "Sears Catalog Home - Wikipedia",
"dateAdd": "2018-07-24T04:19:52.302Z",
"dateUpdate": "2018-07-24T04:20:01.836Z",
"id": "a56de829-5ff8-47de-8d6d-bc66c70d5472",
"type": "url",
"tags": [ "reference", "papers", "wikipedia" ] ,
"images": [],
"description": ""
},{
"url": "https://en.wikipedia.org/wiki/Shapeways",
"name": "Shapeways - Wikipedia",
"dateAdd": "2018-07-24T05:55:38.527Z",
"dateUpdate": "2018-07-24T05:55:38.527Z",
"id": "3260dc6c-8116-47e5-818a-da32ce6bcf68",
"type": "url",
"tags": [ "reference", "papers", "wikipedia" ] ,
"images": [],
"description": ""
},{
"url": "https://en.wikipedia.org/wiki/Sketchfab",
"name": "Sketchfab - Wikipedia",
"dateAdd": "2018-07-24T05:53:54.079Z",
"dateUpdate": "2018-07-24T05:53:54.079Z",
"id": "4b5ac2dc-ff3f-4d4b-ab60-54637fda3a32",
"type": "url",
"tags": [ "reference", "papers", "wikipedia" ] ,
"images": [],
"description": ""
},{
"url": "https://en.wikipedia.org/wiki/Software_architecture",
"name": "Software architecture - Wikipedia",
"dateAdd": "2018-07-20T08:25:40.232Z",
"dateUpdate": "2018-07-20T08:25:40.233Z",
"id": "c2730e49-ffee-4858-b01b-7ad5b862ba62",
"type": "url",
"tags": [ "reference", "papers", "wikipedia" ] ,
"images": [],
"description": ""
},{
"url": "https://en.wikipedia.org/wiki/Thingiverse",
"name": "Thingiverse - Wikipedia",
"dateAdd": "2018-07-19T08:42:54.012Z",
"dateUpdate": "2018-07-24T05:50:26.301Z",
"id": "c9a4a5ee-00ce-4dc9-b30b-e4ae75a5288c",
"type": "url",
"tags": [ "reference", "papers", "wikipedia" ] ,
"images": [],
"description": ""
},{
"url": "https://en.wikipedia.org/wiki/Threeding",
"name": "Threeding - Wikipedia",
"dateAdd": "2018-07-24T05:56:01.607Z",
"dateUpdate": "2018-07-24T05:56:01.607Z",
"id": "eba17492-0eed-498c-9517-d9cf40d4009a",
"type": "url",
"tags": [ "reference", "papers", "wikipedia" ] ,
"images": [],
"description": ""
},{
"url": "https://en.wikipedia.org/wiki/Virtual_Organization_for_Innovative_Conceptual_Engineering_Design",
"name": "Virtual Organization for Innovative Conceptual Engineering Design - Wikipedia",
"dateAdd": "2018-07-20T08:41:47.194Z",
"dateUpdate": "2018-07-24T05:57:16.356Z",
"id": "f26b5201-bb05-4b12-a39c-4e8f24039cc3",
"type": "url",
"tags": [ "reference", "papers", "wikipedia" ] ,
"images": [],
"description": ""
},{
"url": "https://en.wikipedia.org/wiki/WikiHouse",
"name": "WikiHouse - Wikipedia",
"dateAdd": "2018-07-19T08:41:57.065Z",
"dateUpdate": "2018-07-24T05:48:00.496Z",
"id": "427dee9e-3644-488e-90f8-f28630bfa3ed",
"type": "url",
"tags": [ "reference", "papers", "wikipedia" ] ,
"images": [],
"description": ""
},{
"url": "https://github.com/obricks/open-source-architecture",
"name": "obricks/open-source-architecture: A directory of open source architecture ressources: platforms, communities, projects...",
"dateAdd": "2018-07-24T06:25:07.566Z",
"dateUpdate": "2018-07-24T06:25:22.121Z",
"id": "fb7c3375-3fab-4f2f-a6bf-4ed999d323a7",
"type": "url",
"tags": [ "reference", "papers", ] ,
"images": [],
"description": ""
},{
"url": "https://en.wikipedia.org/wiki/Minimum_viable_product",
"name": "Minimum viable product - Wikipedia",
"dateAdd": "2019-01-28T07:59:53.752Z",
"dateUpdate": "2019-01-28T07:59:53.752Z",
"id": "262f1efc-c74a-44b5-a7c0-1f5a195a5167",
"type": "url",
"tags": [ "reference", "minimum-viable-product", "wikipedia" ] ,
"images": [],
"description": ""
},{
"url": "https://steveblank.com/2010/03/04/perfection-by-subtraction-the-minimum-feature-set/",
"name": "Steve Blank Perfection By Subtraction – The Minimum Feature Set",
"dateAdd": "2019-01-28T08:00:56.817Z",
"dateUpdate": "2019-01-28T08:00:56.817Z",
"id": "4fba0d80-7427-4c76-b003-c42ce056d71c",
"type": "url",
"tags": [ "reference", "minimum-viable-product", ] ,
"images": [],
"description": ""
},{
"url": "http://ask.leanstack.com/lean-startup-fundamentals/what-is-a-minimum-viable-product-mvp",
"name": "What is a Minimum Viable Product (MVP)? | Ask LEANSTACK",
"dateAdd": "2019-01-28T08:07:31.499Z",
"dateUpdate": "2019-03-02T09:16:16.564Z",
"id": "3f5a48ea-f444-45e2-9dad-17821df90fe7",
"type": "url",
"tags": [ "reference", "minimum-viable-product", ] ,
"images": [],
"description": ""
},{
"url": "https://medium.freecodecamp.org/what-the-hell-does-minimum-viable-product-actually-mean-anyway-7d8f6a110f38",
"name": "What the hell does “Minimum Viable Product” actually mean anyway?",
"dateAdd": "2019-01-28T08:08:16.747Z",
"dateUpdate": "2019-01-28T08:08:16.748Z",
"id": "797d3cbb-269d-4c56-9a05-44949979f95c",
"type": "url",
"tags": [ "reference", "minimum-viable-product", ] ,
"images": [],
"description": ""
},{
"url": "http://acadia.org/papers",
"name": "ACADIA",
"dateAdd": "2018-08-12T08:40:46.569Z",
"dateUpdate": "2019-04-21T07:39:48.573Z",
"id": "06bf5c5c-d63a-4827-b137-20ea7db8428f",
"type": "url",
"tags": [ "reference", "parametric design", ] ,
"images": [],
"description": ""
},{
"url": "https://en.wikipedia.org/wiki/Design_computing",
"name": "Design computing - Wikipedia",
"dateAdd": "2018-08-12T08:42:28.638Z",
"dateUpdate": "2018-08-12T08:42:28.639Z",
"id": "440fdb0c-d3db-4a8d-810d-573b0044adae",
"type": "url",
"tags": [ "reference", "parametric design", "wikipedia" ] ,
"images": [],
"description": ""
},{
"url": "https://en.wikipedia.org/wiki/Evolutionary_algorithm",
"name": "Evolutionary algorithm - Wikipedia",
"dateAdd": "2018-08-12T08:49:32.675Z",
"dateUpdate": "2018-08-12T08:49:32.676Z",
"id": "ce6de0c3-bdfb-4312-9828-c28e283cca57",
"type": "url",
"tags": [ "reference", "parametric design", "wikipedia" ] ,
"images": [],
"description": ""
},{
"url": "https://en.wikipedia.org/wiki/Generative_design",
"name": "Generative design - Wikipedia",
"dateAdd": "2018-08-12T08:17:10.236Z",
"dateUpdate": "2018-08-12T08:51:50.126Z",
"id": "9e117562-4178-40cd-bbf8-7aefb2663421",
"type": "url",
"tags": [ "reference", "parametric design", "wikipedia" ] ,
"images": [],
"description": ""
},{
"url": "https://en.wikipedia.org/wiki/Parametric_design",
"name": "Parametric design - Wikipedia",
"dateAdd": "2018-08-11T09:29:19.637Z",
"dateUpdate": "2018-08-12T08:11:19.057Z",
"id": "7217c6d9-e948-4485-bf30-207fff50920b",
"type": "url",
"tags": [ "reference", "parametric design", "wikipedia" ] ,
"images": [],
"description": ""
},{
"url": "https://www.architectmagazine.com/design/parametric-design-whats-gotten-lost-amid-the-algorithms_o",
"name": "Parametric Design: What's Gotten Lost Amid the Algorithms | Architect Magazine | Design, Parametric Architecture",
"dateAdd": "2018-08-11T09:30:19.191Z",
"dateUpdate": "2019-03-02T09:11:14.661Z",
"id": "2acdf2b4-d1de-43e7-ad8d-ba6dcee08dc3",
"type": "url",
"tags": [ "reference", "parametric design", ] ,
"images": [],
"description": ""
},{
"url": "https://en.wikipedia.org/wiki/Parametricism",
"name": "Parametricism - Wikipedia",
"dateAdd": "2018-08-12T08:33:52.820Z",
"dateUpdate": "2018-08-12T08:51:51.458Z",
"id": "d1f1a896-2200-4d43-a9b8-a5b1ef2340a6",
"type": "url",
"tags": [ "reference", "parametric design", "wikipedia" ] ,
"images": [],
"description": ""
},{
"url": "https://en.wikipedia.org/wiki/Procedural_modeling",
"name": "Procedural modeling - Wikipedia",
"dateAdd": "2018-08-12T08:20:00.852Z",
"dateUpdate": "2018-08-12T08:20:00.852Z",
"id": "2a0a7566-34fd-4dc5-a80d-ee166ad144ea",
"type": "url",
"tags": [ "reference", "parametric design", "wikipedia" ] ,
"images": [],
"description": ""
},{
"url": "https://en.wikipedia.org/wiki/Visual_programming_language",
"name": "Visual programming language - Wikipedia",
"dateAdd": "2018-08-12T08:37:13.819Z",
"dateUpdate": "2019-02-11T04:42:50.711Z",
"id": "0db7ba19-6f17-441e-b0af-87103bf2e46e",
"type": "url",
"tags": [ "reference", "parametric design", "wikipedia" ] ,
"images": [],
"description": ""
},{
"url": "http://www.parametriccamp.com/en/what-is-parametric-design/",
"name": "WHAT IS PARAMETRIC DESIGN? - ParametricCamp",
"dateAdd": "2018-08-11T09:30:51.787Z",
"dateUpdate": "2018-08-11T09:30:51.787Z",
"id": "fb1168f9-5430-44a3-8bdd-847c7403c423",
"type": "url",
"tags": [ "reference", "parametric design", ] ,
"images": [],
"description": ""
},{
"url": "https://campsyte.com/",
"name": "Campsyte - Book inspiring outdoor venues for offsites and events",
"dateAdd": "2018-07-19T07:17:37.308Z",
"dateUpdate": "2018-07-19T07:17:37.309Z",
"id": "00221ae4-d41b-4f12-ae0b-78bdcba1f807",
"type": "url",
"tags": [ "services", ] ,
"images": [],
"description": ""
},{
"url": "http://3drepo.org/contact/",
"name": "Contact | 3D Repo™ – 3D Version Control System",
"dateAdd": "2017-12-31T19:33:48.000Z",
"dateUpdate": "2018-07-21T08:59:39.321Z",
"id": "ef1c7f27-b783-41e3-9d93-ab2f3e40b844",
"type": "url",
"tags": [ "services", ] ,
"images": [],
"description": ""
},{
"url": "http://beta.openstructures.net/pages/9",
"name": "Page > Guidelines. > show",
"dateAdd": "2018-07-29T09:41:08.521Z",
"dateUpdate": "2019-05-19T04:08:51.640Z",
"id": "7f9bd1af-88f3-4891-b738-6999bdc31e83",
"type": "url",
"tags": [ "services", ] ,
"images": [],
"description": ""
},{
"url": "https://en.wikipedia.org/wiki/Soma_cube",
"name": "Soma cube - Wikipedia",
"dateAdd": "2018-07-30T06:50:08.237Z",
"dateUpdate": "2018-08-04T20:09:33.752Z",
"id": "7c3aadf3-b866-4cc1-9cda-bf69d9e10b12",
"type": "url",
"tags": [ "services", "wikipedia" ] ,
"images": [],
"description": ""
},{
"url": "https://en.wikipedia.org/wiki/Pentomino",
"name": "Pentomino - Wikipedia",
"dateAdd": "2018-07-30T06:52:20.742Z",
"dateUpdate": "2018-07-30T08:49:14.528Z",
"id": "c613ec6f-4fd2-426a-a7f0-d42380fdf80a",
"type": "url",
"tags": [ "services", "wikipedia" ] ,
"images": [],
"description": ""
},{
"url": "https://en.wikipedia.org/wiki/Tetris",
"name": "Tetris - Wikipedia",
"dateAdd": "2018-07-30T06:54:46.951Z",
"dateUpdate": "2018-07-30T06:54:46.952Z",
"id": "65e465a2-5426-4b58-891b-d58707533c8c",
"type": "url",
"tags": [ "services", "wikipedia" ] ,
"images": [],
"description": ""
},{
"url": "https://www.readingdesign.org/250-things",
"name": "Two Hundred Fifty Things an Architect Should Know — R / D",
"dateAdd": "2018-10-24T10:49:27.039Z",
"dateUpdate": "2018-11-05T08:23:46.471Z",
"id": "6ffe93de-ebe5-4efe-9740-b928486f6549",
"type": "url",
"tags": [ "services", ] ,
"images": [],
"description": ""
},{
"url": "https://buildingos.com/login?next=/",
"name": "BuildingOS – Login",
"dateAdd": "2018-11-12T08:32:03.359Z",
"dateUpdate": "2018-12-16T05:23:40.085Z",
"id": "18313d0f-b7fe-4a59-b408-05b784ccd418",
"type": "url",
"tags": [ "services", ] ,
"images": [],
"description": ""
}